Workbook

Sheet 4º RCC - RS

Sheet TUNAS - PR
A1: ESTAMOS OFERENCENDO DESCONTO DE 40,01% EM TODAS AS PASSSAGENS, USAR CALCULADORA A BAIXO PARA SIMPLIFICAR ORCAMENTO
C4: lance | E4: PRC AUMENTO | F4: 0.98664
B5: 0.401 | C5: =B5 -> 0.401 | E5: OBJETIVO | F5: 0.23
A7: CUSTO | B7: VLR REAL | C7: VLR DESCONTO | D7: VLR TOTAL | E7: VLT OBJET | F7: VLR ACRESCIMO | I7: CUSTO | J7: VLR REAL | K7: VLR DESCONTO | L7: VLR TOTAL | M7: VLT OBJET | N7: VLR ACRESCIMO
A8: 13300 | B8: =E8/(1-$B$5) -> 27310.518 | C8: =B8*$C$5 -> 10951.518 | D8: =B8-C8 -> 16359 | E8: =A8+(A8*$F$5) -> 16359 | F8: =B8-A8 -> 14010.518 | I8: 3250 | J8: =M8/(1-$B$5) -> 6673.6227 | K8: =J8*$C$5 -> 2676.1227 | L8: =J8-K8 -> 3997.5 | M8: =I8+(I8*$F$5) -> 3997.5 | N8: =J8-I8 -> 3423.6227
D9: LUCRO | L9: LUCRO
D10: =D8-A8 -> 3059 | L10: =L8-I8 -> 747.5
A11: quantidade pessoa | B11: 7 | F11: TOTAL P PESSOA
A12: =A8/B11 -> 1900 | F12: =D8/B11 -> 2337
A15: SOLICITACAO | B15: NOME | C15: DT NASCIMENTO | D15: CPF | E15: IDA | F15: DESTINO | G15: DATA IDA | H15: DATA VOLTA | I15: CUSTO | J15: VENDA VLR
A16: 45854 | B16: Douglas De Souza Guerreiro | C16: 31992 | D16: 057.372.039-80 | E16: IGU | F16: CWB | G16: 45912 | L16: =2989.11+A8 -> 16289.11
A17: 45854 | B17: Adriano Pereira Xavier | C17: 30505 | D17: 04520613930 | E17: IGU | F17: CWB | G17: 45912 | L17: =SUM(D8,L8) -> 20356.5
A18: 45912 | B18: Adriano Pereira Xavier | C18: =IFERROR(VLOOKUP(B18,'Página8'!A:B,2,0),"") -> 30505 | D18: =IFERROR(VLOOKUP(B18,'Página8'!A:C,3,0),"") -> 04520613930 | E18: CWB | F18: BSB | G18: 45986 | H18: 45989 | I18: 1256.33 | J18: 1487.18 | L18: =L17-L16 -> 4067.39
A19: 45912 | B19: Amailson Mateus dos Santos de jesus | C19: =IFERROR(VLOOKUP(B19,'Página8'!A:B,2,0),"") -> 36191 | D19: =IFERROR(VLOOKUP(B19,'Página8'!A:C,3,0),"") -> 11941708978 | E19: CWB | F19: BSB | G19: 45986 | H19: 45989 | I19: 1256.33 | J19: 1487.18
A20: 45912 | B20: Daniel Sikora | C20: =IFERROR(VLOOKUP(B20,'Página8'!A:B,2,0),"") -> 28963 | D20: =IFERROR(VLOOKUP(B20,'Página8'!A:C,3,0),"") -> 03586628935 | E20: CWB | F20: BSB | G20: 45986 | H20: 45989 | I20: 1256.33 | J20: 1487.18
A21: 45912 | B21: Denise de Fatima dos Santos | C21: =IFERROR(VLOOKUP(B21,'Página8'!A:B,2,0),"") -> 28507 | D21: =IFERROR(VLOOKUP(B21,'Página8'!A:C,3,0),"") -> 02498362975 | E21: CWB | F21: BSB | G21: 45986 | H21: 45989 | I21: 1256.33 | J21: 1487.18
A22: 45912 | B22: Douglas De Souza Guerreiro | C22: =IFERROR(VLOOKUP(B22,'Página8'!A:B,2,0),"") -> 31992 | D22: =IFERROR(VLOOKUP(B22,'Página8'!A:C,3,0),"") -> 057.372.039-80 | E22: CWB | F22: BSB | G22: 45986 | H22: 45989 | I22: 1256.33 | J22: 1487.18
A23: 45912 | B23: Eroildes de Jesus Burkner | C23: =IFERROR(VLOOKUP(B23,'Página8'!A:B,2,0),"") -> 25204 | D23: =IFERROR(VLOOKUP(B23,'Página8'!A:C,3,0),"") -> 766.831.259-53 | E23: CWB | F23: BSB | G23: 45986 | H23: 45989 | I23: 1256.33 | J23: 1487.18
A24: 45912 | B24: Mariza Gonçalves dos Reis Araujo | C24: =IFERROR(VLOOKUP(B24,'Página8'!A:B,2,0),"") -> 20991 | D24: =IFERROR(VLOOKUP(B24,'Página8'!A:C,3,0),"") -> 850.602.759-49 | E24: CWB | F24: BSB | G24: 45986 | H24: 45989 | I24: 1256.33 | J24: 1487.18
A25: 45912 | B25: Josilene Bonete de Faria | C25: =IFERROR(VLOOKUP(B25,'Página8'!A:B,2,0),"") -> 34243 | D25: =IFERROR(VLOOKUP(B25,'Página8'!A:C,3,0),"") -> 08093548963 | E25: CWB | F25: BSB | G25: 45986 | H25: 45988 | I25: 999.59 | J25: 1487.18
A26: 45912 | B26: Kauan Ariel De Souza Bomfim | C26: =IFERROR(VLOOKUP(B26,'Página8'!A:B,2,0),"") -> 37099 | D26: =IFERROR(VLOOKUP(B26,'Página8'!A:C,3,0),"") -> 10789785900 | E26: CWB | F26: BSB | G26: 45986 | H26: 45988 | I26: 999.59 | J26: 1487.18
A27: 45912 | B27: Miriam de Fátima Neres | C27: =IFERROR(VLOOKUP(B27,'Página8'!A:B,2,0),"") -> 31126 | D27: =IFERROR(VLOOKUP(B27,'Página8'!A:C,3,0),"") -> 07877179910 | E27: CWB | F27: BSB | G27: 45986 | H27: 45988 | I27: 999.59 | J27: 1487.18
A28: 45916 | B28: Jair de Oliveira Pereira | C28: =IFERROR(VLOOKUP(B28,'Página8'!A:B,2,0),"") -> 26914 | D28: =IFERROR(VLOOKUP(B28,'Página8'!A:C,3,0),"") -> 93884710915 | E28: CWB | F28: BSB | G28: 45986 | H28: 45989 | I28: 1256.33 | J28: 1487.18
C29: =IFERROR(VLOOKUP(B29,'Página8'!A:B,2,0),"") | D29: =IFERROR(VLOOKUP(B29,'Página8'!A:C,3,0),"") | I29: =SUM(I16:I28) -> 13049.41 | J29: =SUM(J16:J28) -> 16358.98 | K29: =J29-I29 -> 3309.57
C30: =IFERROR(VLOOKUP(B30,'Página8'!A:B,2,0),"") | D30: =IFERROR(VLOOKUP(B30,'Página8'!A:C,3,0),"")
C31: =IFERROR(VLOOKUP(B31,'Página8'!A:B,2,0),"") | D31: =IFERROR(VLOOKUP(B31,'Página8'!A:C,3,0),"")
C32: =IFERROR(VLOOKUP(B32,'Página8'!A:B,2,0),"") | D32: =IFERROR(VLOOKUP(B32,'Página8'!A:C,3,0),"")
C33: =IFERROR(VLOOKUP(B33,'Página8'!A:B,2,0),"") | D33: =IFERROR(VLOOKUP(B33,'Página8'!A:C,3,0),"")
C34: =IFERROR(VLOOKUP(B34,'Página8'!A:B,2,0),"") | D34: =IFERROR(VLOOKUP(B34,'Página8'!A:C,3,0),"")
C35: =IFERROR(VLOOKUP(B35,'Página8'!A:B,2,0),"") | D35: =IFERROR(VLOOKUP(B35,'Página8'!A:C,3,0),"")
C36: =IFERROR(VLOOKUP(B36,'Página8'!A:B,2,0),"") | D36: =IFERROR(VLOOKUP(B36,'Página8'!A:C,3,0),"")
A47: 25763200 Passagens,
A48: 100 idas e 100
A49: voltas200R$R$
A50: 25763200 Passagens,
A51: 100 idas e 100
A52: voltas200R$R$
A53: TOTAL:R$R$

Sheet 6º RCC - RS
A1: DATA SOLICITACAO | B1: DATA IDA | C1: DATA CHEGADA | D1: DE | E1: PARA | F1: HORARIO SAIDA | G1: HORARIO CHEGADA | H1: ASSENTO | I1: BILHETE | J1: CLASSE | K1: COLABORADOR | L1: CPF | M1: DT NASC | N1: VALOR | O1: CUSTO | P1: LUCRO | Q1: PERCENTIL | R1: Pago
A2: 45852 | B2: 45856 | C2: 45856 | D2: ALEGRETTE | E2: PORTO ALEGRE | F2: 0.10416667 | G2: 0.47916667 | H2: 9 | I2: 10065308799462 | J2: LEITO | K2: LUIZ GUSTAVO GONÇALVES DA SILVA | L2: 216.767.587-98 | M2: 37484 | N2: 624.7 | O2: 479.91 | P2: =N2-O2 -> 144.79 | Q2: =P2/N2 -> 0.23177525
A3: 45852 | B3: 45856 | C3: 45856 | D3: ALEGRETTE | E3: PORTO ALEGRE | F3: 0.10416667 | G3: 0.47916667 | H3: 2 | I3: 10065308799392 | J3: LEITO | K3: LOHAN WELLINGTON ROGACIANO DA SILVA | L3: 184.390.037-81 | M3: 36664 | N3: 624.7 | O3: 479.91 | P3: =N3-O3 -> 144.79 | Q3: =P3/N3 -> 0.23177525
A4: 45852 | B4: 45856 | C4: 45856 | D4: ALEGRETTE | E4: PORTO ALEGRE | F4: 0.10416667 | G4: 0.47916667 | H4: 6 | I4: 10065308799453 | J4: LEITO | K4: JOSÉ CARLOS ALVES DE SANTA ROSA | L4: 711.275.044-01 | M4: 39152 | N4: 624.7 | O4: 479.91 | P4: =N4-O4 -> 144.79 | Q4: =P4/N4 -> 0.23177525
A5: 45852 | B5: 45856 | C5: 45857 | D5: PORTO ALEGRE | E5: SAO PAULO TIETE | F5: 0.54166667 | G5: 0.41666667 | H5: 50 | I5: 010285313128 | J5: LEITO-CAMA | K5: LUIZ GUSTAVO GONÇALVES DA SILVA | L5: 216.767.587-98 | M5: 37484 | N5: 1130.2 | O5: 1009.5 | P5: =N5-O5 -> 120.7 | Q5: =P5/N5 -> 0.10679526
A6: 45852 | B6: 45856 | C6: 45857 | D6: PORTO ALEGRE | E6: SAO PAULO TIETE | F6: 0.54166667 | G6: 0.41666667 | H6: 53 | I6: 010285313129 | J6: LEITO-CAMA | K6: LOHAN WELLINGTON ROGACIANO DA SILVA | L6: 184.390.037-81 | M6: 36664 | N6: 1130.2 | O6: 1009.5 | P6: =N6-O6 -> 120.7 | Q6: =P6/N6 -> 0.10679526
A7: 45852 | B7: 45856 | C7: 45857 | D7: PORTO ALEGRE | E7: SAO PAULO TIETE | F7: 0.54166667 | G7: 0.41666667 | H7: 52 | I7: 010285313130 | J7: LEITO-CAMA | K7: JOSÉ CARLOS ALVES DE SANTA ROSA | L7: 711.275.044-01 | M7: 39152 | N7: 1130.2 | O7: 1009.5 | P7: =N7-O7 -> 120.7 | Q7: =P7/N7 -> 0.10679526
A8: 45852 | B8: 45857 | C8: 45857 | D8: SAO PAULO TIETE | E8: TAUBATE | F8: 0.5 | G8: 0.58333333 | H8: 31 | I8: 010227540217 | J8: CONVENCIONAL | K8: LUIZ GUSTAVO GONÇALVES DA SILVA | L8: 216.767.587-98 | M8: 37484 | N8: 189.3 | O8: 76.02 | P8: =N8-O8 -> 113.28 | Q8: =P8/N8 -> 0.59841521
A9: 45852 | B9: 45857 | C9: 45857 | D9: SAO PAULO TIETE | E9: TAUBATE | F9: 0.5 | G9: 0.58333333 | H9: 32 | I9: 010227540216 | J9: CONVENCIONAL | K9: LOHAN WELLINGTON ROGACIANO DA SILVA | L9: 184.390.037-81 | M9: 36664 | N9: 189.3 | O9: 76.02 | P9: =N9-O9 -> 113.28 | Q9: =P9/N9 -> 0.59841521
A10: 45852 | B10: 45857 | C10: 45857 | D10: SAO PAULO TIETE | E10: TAUBATE | F10: 0.5 | G10: 0.58333333 | H10: 35 | I10: 010227540215 | J10: CONVENCIONAL | K10: JOSÉ CARLOS ALVES DE SANTA ROSA | L10: 711.275.044-01 | M10: 39152 | N10: 189.3 | O10: 76.02 | P10: =N10-O10 -> 113.28 | Q10: =P10/N10 -> 0.59841521
M11: TOTAL | N11: =SUM(N2:N10) -> 5832.6 | O11: =SUM(O2:O10) -> 4696.29 | P11: =N11-O11 -> 1136.31 | Q11: =P11/N11 -> 0.19482049
R12: Sim
K15: 6507.4
C16: DATA | D16: DE | E16: PARA | F16: VALOR | K16: =K15/4 -> 1626.85
C17: 45687 | D17: ALEGRETTE | E17: PORTO ALEGRE | F17: 624.7 | G17: =F17/SUM(F$17:F$20) -> 0.31817256 | H17: 517.62
C18: 45688 | D18: CAMPINAS | E18: TRES CORACOES | F18: 357 | G18: =F18/SUM(F$17:F$20) -> 0.18182744 | H18: 295.01
C19: 45694 | D19: TRES CORACOES | E19: CAMPINAS | F19: 357 | G19: =F19/SUM(F$17:F$20) -> 0.18182744 | H19: 295
C20: 45695 | D20: PORTO ALEGRE | E20: ALEGRETTE | F20: 624.7 | G20: =F20/SUM(F$17:F$20) -> 0.31817256 | H20: 517.62

Sheet 13º RCM - SP
A1: DATA SOLICITACAO | B1: DATA IDA | C1: DATA CHEGADA | D1: DE | E1: PARA | F1: HORARIO SAIDA | G1: HORARIO CHEGADA | H1: ASSENTO | I1: BILHETE | J1: CLASSE | K1: COLABORADOR | L1: CPF | M1: DT NASC | N1: VALOR | O1: CUSTO | P1: LUCRO | Q1: PERCENTIL | R1: pago
A2: 45852 | B2: 45858 | C2: 45858 | D2: PIRASSUNUNGA | E2: TIETE | F2: 0.34375 | G2: 0.46875 | H2: 23 | I2: 010008502928 | J2: CONVENCIONAL | K2: GABRIEL ALVES MOREIRA | L2: 146.734.667-56 | M2: 37757 | N2: 496.99 | O2: 386.4 | P2: =N2-O2 -> 110.59 | Q2: =P2/N2 -> 0.22251957
A3: 45852 | B3: 45858 | C3: 45858 | D3: PIRASSUNUNGA | E3: TIETE | F3: 0.34375 | G3: 0.46875 | H3: 20 | I3: 010008502932 | J3: CONVENCIONAL | K3: MATEUS DA SILVA VALERIO | L3: 176.791.447-45 | M3: 37515 | N3: 496.99 | O3: 386.4 | P3: =N3-O3 -> 110.59 | Q3: =P3/N3 -> 0.22251957
A4: 45852 | B4: 45858 | C4: 45858 | D4: PIRASSUNUNGA | E4: TIETE | F4: 0.34375 | G4: 0.46875 | H4: 14 | I4: 010008503000 | J4: CONVENCIONAL | K4: VICTOR HUGO BARROS DASINGER | L4: 172.512.107-70 | M4: 38102 | N4: 496.99 | O4: 386.4 | P4: =N4-O4 -> 110.59 | Q4: =P4/N4 -> 0.22251957
A5: 45852 | B5: 45858 | C5: 45858 | D5: PIRASSUNUNGA | E5: TIETE | F5: 0.34375 | G5: 0.46875 | H5: 10 | I5: 010008503001 | J5: CONVENCIONAL | K5: GABRIEL PAULO DA SILVA | L5: 164.408.617-43 | M5: 38270 | N5: 496.99 | O5: 386.4 | P5: =N5-O5 -> 110.59 | Q5: =P5/N5 -> 0.22251957
A6: 45852 | B6: 45858 | C6: 45858 | D6: PIRASSUNUNGA | E6: TIETE | F6: 0.34375 | G6: 0.46875 | H6: 15 | I6: 010008502929 | J6: CONVENCIONAL | K6: THEO CASINI ROCHA | L6: 192.455.347-31 | M6: 38523 | N6: 496.99 | O6: 386.4 | P6: =N6-O6 -> 110.59 | Q6: =P6/N6 -> 0.22251957
A7: 45852 | B7: 45858 | C7: 45858 | D7: PIRASSUNUNGA | E7: TIETE | F7: 0.34375 | G7: 0.46875 | H7: 19 | I7: 010008502935 | J7: CONVENCIONAL | K7: JUAN PABLO DE CARVALHO ROCHO | L7: 711.524.794-31 | M7: 37770 | N7: 496.99 | O7: 386.4 | P7: =N7-O7 -> 110.59 | Q7: =P7/N7 -> 0.22251957
A8: 45852 | B8: 45858 | C8: 45858 | D8: PIRASSUNUNGA | E8: TIETE | F8: 0.34375 | G8: 0.46875 | H8: 8 | I8: 010008502934 | J8: CONVENCIONAL | K8: BRUNO CORDEIRO NEVES | L8: 146.647.817-92 | M8: 37395 | N8: 496.99 | O8: 386.4 | P8: =N8-O8 -> 110.59 | Q8: =P8/N8 -> 0.22251957
A9: 45852 | B9: 45858 | C9: 45858 | D9: PIRASSUNUNGA | E9: TIETE | F9: 0.34375 | G9: 0.46875 | H9: 4 | I9: 010008502933 | J9: CONVENCIONAL | K9: RAFAEL CAETANO COSTA | L9: 162.084.366-80 | M9: 37474 | N9: 496.99 | O9: 386.4 | P9: =N9-O9 -> 110.59 | Q9: =P9/N9 -> 0.22251957
A10: 45852 | B10: 45858 | C10: 45858 | D10: PIRASSUNUNGA | E10: TIETE | F10: 0.34375 | G10: 0.46875 | H10: 9 | I10: 010008503002 | J10: CONVENCIONAL | K10: MATEUS PEREIRA SILVA | L10: 133.834.544-36 | M10: 38335 | N10: 496.99 | O10: 386.4 | P10: =N10-O10 -> 110.59 | Q10: =P10/N10 -> 0.22251957
A11: 45852 | B11: 45858 | C11: 45858 | D11: PIRASSUNUNGA | E11: TIETE | F11: 0.34375 | G11: 0.46875 | H11: 7 | I11: 010008502931 | J11: CONVENCIONAL | K11: CRISTOFER DA SILVA PEREIRA | L11: 135.374.767-01 | M11: 38096 | N11: 496.99 | O11: 386.4 | P11: =N11-O11 -> 110.59 | Q11: =P11/N11 -> 0.22251957
A12: 45852 | B12: 45858 | C12: 45858 | D12: PIRASSUNUNGA | E12: TIETE | F12: 0.34375 | G12: 0.46875 | H12: 5 | I12: 010008503003 | J12: CONVENCIONAL | K12: PEDRO LEONEL BASTOS | L12: 160.738.187-77 | M12: 38702 | N12: 496.99 | O12: 386.4 | P12: =N12-O12 -> 110.59 | Q12: =P12/N12 -> 0.22251957
A13: 45852 | B13: 45858 | C13: 45858 | D13: TIETE | E13: TAUBATE | F13: 0.54166667 | G13: 0.64583333 | H13: 15 | I13: 010227542552 | J13: CONVENCIONAL | K13: GABRIEL ALVES MOREIRA | L13: 146.734.667-56 | M13: 37757
A14: 45852 | B14: 45858 | C14: 45858 | D14: TIETE | E14: TAUBATE | F14: 0.54166667 | G14: 0.64583333 | H14: 19 | I14: 010227542559 | J14: CONVENCIONAL | K14: MATEUS DA SILVA VALERIO | L14: 176.791.447-45 | M14: 37515
A15: 45852 | B15: 45858 | C15: 45858 | D15: TIETE | E15: TAUBATE | F15: 0.54166667 | G15: 0.64583333 | H15: 23 | I15: 010227542550 | J15: CONVENCIONAL | K15: VICTOR HUGO BARROS DASINGER | L15: 172.512.107-70 | M15: 38102
A16: 45852 | B16: 45858 | C16: 45858 | D16: TIETE | E16: TAUBATE | F16: 0.54166667 | G16: 0.64583333 | H16: 16 | I16: 010227542558 | J16: CONVENCIONAL | K16: GABRIEL PAULO DA SILVA | L16: 164.408.617-43 | M16: 38270
A17: 45852 | B17: 45858 | C17: 45858 | D17: TIETE | E17: TAUBATE | F17: 0.54166667 | G17: 0.64583333 | H17: 12 | I17: 010227542554 | J17: CONVENCIONAL | K17: THEO CASINI ROCHA | L17: 192.455.347-31 | M17: 38523
A18: 45852 | B18: 45858 | C18: 45858 | D18: TIETE | E18: TAUBATE | F18: 0.54166667 | G18: 0.64583333 | H18: 27 | I18: 010227542557 | J18: CONVENCIONAL | K18: JUAN PABLO DE CARVALHO ROCHO | L18: 711.524.794-31 | M18: 37770
A19: 45852 | B19: 45858 | C19: 45858 | D19: TIETE | E19: TAUBATE | F19: 0.54166667 | G19: 0.64583333 | H19: 20 | I19: 010227542560 | J19: CONVENCIONAL | K19: BRUNO CORDEIRO NEVES | L19: 146.647.817-92 | M19: 37395
A20: 45852 | B20: 45858 | C20: 45858 | D20: TIETE | E20: TAUBATE | F20: 0.54166667 | G20: 0.64583333 | H20: 24 | I20: 010227542553 | J20: CONVENCIONAL | K20: RAFAEL CAETANO COSTA | L20: 162.084.366-80 | M20: 37474
A21: 45852 | B21: 45858 | C21: 45858 | D21: TIETE | E21: TAUBATE | F21: 0.54166667 | G21: 0.64583333 | H21: 28 | I21: 010227542556 | J21: CONVENCIONAL | K21: MATEUS PEREIRA SILVA | L21: 133.834.544-36 | M21: 38335
A22: 45852 | B22: 45858 | C22: 45858 | D22: TIETE | E22: TAUBATE | F22: 0.54166667 | G22: 0.64583333 | H22: 31 | I22: 010227542551 | J22: CONVENCIONAL | K22: CRISTOFER DA SILVA PEREIRA | L22: 135.374.767-01 | M22: 38096
A23: 45852 | B23: 45858 | C23: 45858 | D23: TIETE | E23: TAUBATE | F23: 0.54166667 | G23: 0.64583333 | H23: 11 | I23: 010227542555 | J23: CONVENCIONAL | K23: PEDRO LEONEL BASTOS | L23: 160.738.187-77 | M23: 38702
A24: 45852 | B24: 45863 | C24: 45863 | D24: TAUBATE | E24: TIETE | F24: 0.54166667 | G24: 0.63888889 | H24: 3 | I24: 010227542565 | N24: =SUM(N2:N23) -> 5466.89 | R24: Ok
D25: - | E25: -
D26: - | E26: -
D27: - | E27: -

Sheet Página8
A1: NOME | B1: DATA NASC | C1: CPF
A2: =IFERROR(__xludf.DUMMYFUNCTION("IMPORTRANGE(""https://docs.google.com/spreadsheets/d/1aTvIrqNmmcWMKGcvTQK3YcRRqao-8Pnts2s5Mjh-jtA/edit?gid=0#gid=0"",""PASSAGEIROS!C2:e500"")"),"Gabriela Camargo Flose") -> Gabriela Camargo Flose | B2: =IFERROR(__xludf.DUMMYFUNCTION("""COMPUTED_VALUE"""),36638.0) -> 36638 | C2: =IFERROR(__xludf.DUMMYFUNCTION("""COMPUTED_VALUE"""),"51324394897") -> 51324394897
A3: =IFERROR(__xludf.DUMMYFUNCTION("""COMPUTED_VALUE"""),"Gabriel Venâncio Georgino") -> Gabriel Venâncio Georgino | B3: =IFERROR(__xludf.DUMMYFUNCTION("""COMPUTED_VALUE"""),35465.0) -> 35465 | C3: =IFERROR(__xludf.DUMMYFUNCTION("""COMPUTED_VALUE"""),"45662704830") -> 45662704830
A4: =IFERROR(__xludf.DUMMYFUNCTION("""COMPUTED_VALUE"""),"Graziela Ribeiro Caires") -> Graziela Ribeiro Caires | B4: =IFERROR(__xludf.DUMMYFUNCTION("""COMPUTED_VALUE"""),35674.0) -> 35674 | C4: =IFERROR(__xludf.DUMMYFUNCTION("""COMPUTED_VALUE"""),"47208941866") -> 47208941866
A5: =IFERROR(__xludf.DUMMYFUNCTION("""COMPUTED_VALUE"""),"Marcos Adriano Victor de Morais") -> Marcos Adriano Victor de Morais | B5: =IFERROR(__xludf.DUMMYFUNCTION("""COMPUTED_VALUE"""),34373.0) -> 34373 | C5: =IFERROR(__xludf.DUMMYFUNCTION("""COMPUTED_VALUE"""),"01739570480") -> 01739570480
A6: =IFERROR(__xludf.DUMMYFUNCTION("""COMPUTED_VALUE"""),"Paula Passos Ferreira ") -> Paula Passos Ferreira | B6: =IFERROR(__xludf.DUMMYFUNCTION("""COMPUTED_VALUE"""),33995.0) -> 33995 | C6: =IFERROR(__xludf.DUMMYFUNCTION("""COMPUTED_VALUE"""),"406.588.548-52 ") -> 406.588.548-52
A7: =IFERROR(__xludf.DUMMYFUNCTION("""COMPUTED_VALUE"""),"Danilo Gomes da Silva ") -> Danilo Gomes da Silva | B7: =IFERROR(__xludf.DUMMYFUNCTION("""COMPUTED_VALUE"""),33253.0) -> 33253 | C7: =IFERROR(__xludf.DUMMYFUNCTION("""COMPUTED_VALUE"""),3.9125065823E10) -> 39125065823
A8: =IFERROR(__xludf.DUMMYFUNCTION("""COMPUTED_VALUE"""),"Gustavo Alves de Oliveira ") -> Gustavo Alves de Oliveira | B8: =IFERROR(__xludf.DUMMYFUNCTION("""COMPUTED_VALUE"""),36777.0) -> 36777 | C8: =IFERROR(__xludf.DUMMYFUNCTION("""COMPUTED_VALUE"""),5.0470355816E10) -> 50470355816
A9: =IFERROR(__xludf.DUMMYFUNCTION("""COMPUTED_VALUE"""),"Jonathan Soares Souza") -> Jonathan Soares Souza | B9: =IFERROR(__xludf.DUMMYFUNCTION("""COMPUTED_VALUE"""),35435.0) -> 35435 | C9: =IFERROR(__xludf.DUMMYFUNCTION("""COMPUTED_VALUE"""),4.5142516826E10) -> 45142516826
A10: =IFERROR(__xludf.DUMMYFUNCTION("""COMPUTED_VALUE"""),"Thayná Almeida Calais") -> Thayná Almeida Calais | B10: =IFERROR(__xludf.DUMMYFUNCTION("""COMPUTED_VALUE"""),37893.0) -> 37893 | C10: =IFERROR(__xludf.DUMMYFUNCTION("""COMPUTED_VALUE"""),5.5535342831E10) -> 55535342831
A11: =IFERROR(__xludf.DUMMYFUNCTION("""COMPUTED_VALUE"""),"Fabiana Letícia Baldo ") -> Fabiana Letícia Baldo | B11: =IFERROR(__xludf.DUMMYFUNCTION("""COMPUTED_VALUE"""),32208.0) -> 32208 | C11: =IFERROR(__xludf.DUMMYFUNCTION("""COMPUTED_VALUE"""),"358.806.428-10 ") -> 358.806.428-10
A12: =IFERROR(__xludf.DUMMYFUNCTION("""COMPUTED_VALUE"""),"Nicole de Souza Okinokabu") -> Nicole de Souza Okinokabu | B12: =IFERROR(__xludf.DUMMYFUNCTION("""COMPUTED_VALUE"""),34742.0) -> 34742 | C12: =IFERROR(__xludf.DUMMYFUNCTION("""COMPUTED_VALUE"""),"06568145947") -> 06568145947
A13: =IFERROR(__xludf.DUMMYFUNCTION("""COMPUTED_VALUE"""),"Milaine Cezero Pimenta de Souza") -> Milaine Cezero Pimenta de Souza | B13: =IFERROR(__xludf.DUMMYFUNCTION("""COMPUTED_VALUE"""),26702.0) -> 26702 | C13: =IFERROR(__xludf.DUMMYFUNCTION("""COMPUTED_VALUE"""),1.6544944882E10) -> 16544944882
A14: =IFERROR(__xludf.DUMMYFUNCTION("""COMPUTED_VALUE"""),"Raphael Antonio Holanda Rodrigues") -> Raphael Antonio Holanda Rodrigues | B14: =IFERROR(__xludf.DUMMYFUNCTION("""COMPUTED_VALUE"""),32911.0) -> 32911 | C14: =IFERROR(__xludf.DUMMYFUNCTION("""COMPUTED_VALUE"""),"230.629.968-46") -> 230.629.968-46
A15: =IFERROR(__xludf.DUMMYFUNCTION("""COMPUTED_VALUE"""),"Katarina Holanda Okinokabu") -> Katarina Holanda Okinokabu | B15: =IFERROR(__xludf.DUMMYFUNCTION("""COMPUTED_VALUE"""),45364.0) -> 45364 | C15: =IFERROR(__xludf.DUMMYFUNCTION("""COMPUTED_VALUE"""),"025.144.678-61") -> 025.144.678-61
A16: =IFERROR(__xludf.DUMMYFUNCTION("""COMPUTED_VALUE"""),"Ada de Almeida Medeiros Porcino ") -> Ada de Almeida Medeiros Porcino | B16: =IFERROR(__xludf.DUMMYFUNCTION("""COMPUTED_VALUE"""),29590.0) -> 29590 | C16: =IFERROR(__xludf.DUMMYFUNCTION("""COMPUTED_VALUE"""),3.0602070899E10) -> 30602070899
A17: =IFERROR(__xludf.DUMMYFUNCTION("""COMPUTED_VALUE"""),"Gledson Costa Porcino ") -> Gledson Costa Porcino | B17: =IFERROR(__xludf.DUMMYFUNCTION("""COMPUTED_VALUE"""),28764.0) -> 28764 | C17: =IFERROR(__xludf.DUMMYFUNCTION("""COMPUTED_VALUE"""),2.65232898E10) -> 26523289800
A18: =IFERROR(__xludf.DUMMYFUNCTION("""COMPUTED_VALUE"""),"Tiago Kenji Komessu Coito ") -> Tiago Kenji Komessu Coito | B18: =IFERROR(__xludf.DUMMYFUNCTION("""COMPUTED_VALUE"""),33031.0) -> 33031 | C18: =IFERROR(__xludf.DUMMYFUNCTION("""COMPUTED_VALUE"""),3.9605583844E10) -> 39605583844
A19: =IFERROR(__xludf.DUMMYFUNCTION("""COMPUTED_VALUE"""),"Nathalia Lepore Lopes ") -> Nathalia Lepore Lopes | B19: =IFERROR(__xludf.DUMMYFUNCTION("""COMPUTED_VALUE"""),35956.0) -> 35956 | C19: =IFERROR(__xludf.DUMMYFUNCTION("""COMPUTED_VALUE"""),4.5374636863E10) -> 45374636863
A20: =IFERROR(__xludf.DUMMYFUNCTION("""COMPUTED_VALUE"""),"Gustavo Sanches Sanni") -> Gustavo Sanches Sanni | B20: =IFERROR(__xludf.DUMMYFUNCTION("""COMPUTED_VALUE"""),35390.0) -> 35390 | C20: =IFERROR(__xludf.DUMMYFUNCTION("""COMPUTED_VALUE"""),4.2510078836E10) -> 42510078836
A21: =IFERROR(__xludf.DUMMYFUNCTION("""COMPUTED_VALUE"""),"André Luiz de Araujo") -> André Luiz de Araujo | B21: =IFERROR(__xludf.DUMMYFUNCTION("""COMPUTED_VALUE"""),30010.0) -> 30010 | C21: =IFERROR(__xludf.DUMMYFUNCTION("""COMPUTED_VALUE"""),2.2299594841E10) -> 22299594841
A22: =IFERROR(__xludf.DUMMYFUNCTION("""COMPUTED_VALUE"""),"Jaqueline Stefani Ferreira da Rocha ") -> Jaqueline Stefani Ferreira da Rocha | B22: =IFERROR(__xludf.DUMMYFUNCTION("""COMPUTED_VALUE"""),37208.0) -> 37208 | C22: =IFERROR(__xludf.DUMMYFUNCTION("""COMPUTED_VALUE"""),5.0628546874E10) -> 50628546874
A23: =IFERROR(__xludf.DUMMYFUNCTION("""COMPUTED_VALUE"""),"Daniel Pereira Ramos") -> Daniel Pereira Ramos | B23: =IFERROR(__xludf.DUMMYFUNCTION("""COMPUTED_VALUE"""),36190.0) -> 36190 | C23: =IFERROR(__xludf.DUMMYFUNCTION("""COMPUTED_VALUE"""),4.0544523881E10) -> 40544523881
A24: =IFERROR(__xludf.DUMMYFUNCTION("""COMPUTED_VALUE"""),"João Pedro da Silva Pereira ") -> João Pedro da Silva Pereira | B24: =IFERROR(__xludf.DUMMYFUNCTION("""COMPUTED_VALUE"""),44454.0) -> 44454 | C24: =IFERROR(__xludf.DUMMYFUNCTION("""COMPUTED_VALUE"""),5.9672259867E10) -> 59672259867
A25: =IFERROR(__xludf.DUMMYFUNCTION("""COMPUTED_VALUE"""),"Esberto Silva Ramos") -> Esberto Silva Ramos | B25: =IFERROR(__xludf.DUMMYFUNCTION("""COMPUTED_VALUE"""),22783.0) -> 22783 | C25: =IFERROR(__xludf.DUMMYFUNCTION("""COMPUTED_VALUE"""),2.26665755E10) -> 22666575500
A26: =IFERROR(__xludf.DUMMYFUNCTION("""COMPUTED_VALUE"""),"Cristiniana Pereira Ramos ") -> Cristiniana Pereira Ramos | B26: =IFERROR(__xludf.DUMMYFUNCTION("""COMPUTED_VALUE"""),26164.0) -> 26164 | C26: =IFERROR(__xludf.DUMMYFUNCTION("""COMPUTED_VALUE"""),"717354885-34 ") -> 717354885-34
A27: =IFERROR(__xludf.DUMMYFUNCTION("""COMPUTED_VALUE"""),"Gabriela Alves dos Reis Schunck") -> Gabriela Alves dos Reis Schunck | B27: =IFERROR(__xludf.DUMMYFUNCTION("""COMPUTED_VALUE"""),35893.0) -> 35893 | C27: =IFERROR(__xludf.DUMMYFUNCTION("""COMPUTED_VALUE"""),4.8060147889E10) -> 48060147889
A28: =IFERROR(__xludf.DUMMYFUNCTION("""COMPUTED_VALUE"""),"Felipe Nunes Quinonez") -> Felipe Nunes Quinonez | B28: =IFERROR(__xludf.DUMMYFUNCTION("""COMPUTED_VALUE"""),37933.0) -> 37933 | C28: =IFERROR(__xludf.DUMMYFUNCTION("""COMPUTED_VALUE"""),4.4267735808E10) -> 44267735808
A29: =IFERROR(__xludf.DUMMYFUNCTION("""COMPUTED_VALUE"""),"Laura Tomáz de Aquino") -> Laura Tomáz de Aquino | B29: =IFERROR(__xludf.DUMMYFUNCTION("""COMPUTED_VALUE"""),36159.0) -> 36159 | C29: =IFERROR(__xludf.DUMMYFUNCTION("""COMPUTED_VALUE"""),4.6555802839E10) -> 46555802839
A30: =IFERROR(__xludf.DUMMYFUNCTION("""COMPUTED_VALUE"""),"Tamara Nascimento Soares Cavalcante ") -> Tamara Nascimento Soares Cavalcante | B30: =IFERROR(__xludf.DUMMYFUNCTION("""COMPUTED_VALUE"""),34654.0) -> 34654 | C30: =IFERROR(__xludf.DUMMYFUNCTION("""COMPUTED_VALUE"""),4.2296125832E10) -> 42296125832
A31: =IFERROR(__xludf.DUMMYFUNCTION("""COMPUTED_VALUE"""),"Carlos Henrique monte Cavalcante ") -> Carlos Henrique monte Cavalcante | B31: =IFERROR(__xludf.DUMMYFUNCTION("""COMPUTED_VALUE"""),34023.0) -> 34023 | C31: =IFERROR(__xludf.DUMMYFUNCTION("""COMPUTED_VALUE"""),"230.394.748-04") -> 230.394.748-04
A32: =IFERROR(__xludf.DUMMYFUNCTION("""COMPUTED_VALUE"""),"Rebeca Gomes Lemos") -> Rebeca Gomes Lemos | B32: =IFERROR(__xludf.DUMMYFUNCTION("""COMPUTED_VALUE"""),37242.0) -> 37242 | C32: =IFERROR(__xludf.DUMMYFUNCTION("""COMPUTED_VALUE"""),4.8929657826E10) -> 48929657826
A33: =IFERROR(__xludf.DUMMYFUNCTION("""COMPUTED_VALUE"""),"Karina rosa da silva ") -> Karina rosa da silva | B33: =IFERROR(__xludf.DUMMYFUNCTION("""COMPUTED_VALUE"""),30460.0) -> 30460 | C33: =IFERROR(__xludf.DUMMYFUNCTION("""COMPUTED_VALUE"""),"310.792.988-35 ") -> 310.792.988-35
A34: =IFERROR(__xludf.DUMMYFUNCTION("""COMPUTED_VALUE"""),"Suellen de Oliveira") -> Suellen de Oliveira | B34: =IFERROR(__xludf.DUMMYFUNCTION("""COMPUTED_VALUE"""),35011.0) -> 35011 | C34: =IFERROR(__xludf.DUMMYFUNCTION("""COMPUTED_VALUE"""),"420.282.348-65") -> 420.282.348-65
A35: =IFERROR(__xludf.DUMMYFUNCTION("""COMPUTED_VALUE"""),"JOELMA CLÁUDIA SILVEIRA RIBEIRO") -> JOELMA CLÁUDIA SILVEIRA RIBEIRO | B35: =IFERROR(__xludf.DUMMYFUNCTION("""COMPUTED_VALUE"""),27096.0) -> 27096 | C35: =IFERROR(__xludf.DUMMYFUNCTION("""COMPUTED_VALUE"""),"900801815-20") -> 900801815-20
A36: =IFERROR(__xludf.DUMMYFUNCTION("""COMPUTED_VALUE"""),"Thamires Barros da Silva ") -> Thamires Barros da Silva | B36: =IFERROR(__xludf.DUMMYFUNCTION("""COMPUTED_VALUE"""),36781.0) -> 36781 | C36: =IFERROR(__xludf.DUMMYFUNCTION("""COMPUTED_VALUE"""),4.8620195875E10) -> 48620195875
A37: =IFERROR(__xludf.DUMMYFUNCTION("""COMPUTED_VALUE"""),"Michelli Alves Santana ") -> Michelli Alves Santana | B37: =IFERROR(__xludf.DUMMYFUNCTION("""COMPUTED_VALUE"""),35036.0) -> 35036 | C37: =IFERROR(__xludf.DUMMYFUNCTION("""COMPUTED_VALUE"""),4.4186897883E10) -> 44186897883
A38: =IFERROR(__xludf.DUMMYFUNCTION("""COMPUTED_VALUE"""),"Vitor Henrique Boís Ramos ") -> Vitor Henrique Boís Ramos | B38: =IFERROR(__xludf.DUMMYFUNCTION("""COMPUTED_VALUE"""),35970.0) -> 35970 | C38: =IFERROR(__xludf.DUMMYFUNCTION("""COMPUTED_VALUE"""),4.8018459835E10) -> 48018459835
A39: =IFERROR(__xludf.DUMMYFUNCTION("""COMPUTED_VALUE"""),"Juliane Ramos Lima ") -> Juliane Ramos Lima | B39: =IFERROR(__xludf.DUMMYFUNCTION("""COMPUTED_VALUE"""),35067.0) -> 35067 | C39: =IFERROR(__xludf.DUMMYFUNCTION("""COMPUTED_VALUE"""),"434.934. 448-96") -> 434.934. 448-96
A40: =IFERROR(__xludf.DUMMYFUNCTION("""COMPUTED_VALUE"""),"Gabriela Alves dos Reis Schunck") -> Gabriela Alves dos Reis Schunck | B40: =IFERROR(__xludf.DUMMYFUNCTION("""COMPUTED_VALUE"""),35893.0) -> 35893 | C40: =IFERROR(__xludf.DUMMYFUNCTION("""COMPUTED_VALUE"""),4.8060147889E10) -> 48060147889
A41: =IFERROR(__xludf.DUMMYFUNCTION("""COMPUTED_VALUE"""),"Carlos Eduardo Schunck dos Reis ") -> Carlos Eduardo Schunck dos Reis | B41: =IFERROR(__xludf.DUMMYFUNCTION("""COMPUTED_VALUE"""),41900.0) -> 41900 | C41: =IFERROR(__xludf.DUMMYFUNCTION("""COMPUTED_VALUE"""),4.8961840843E10) -> 48961840843
A42: =IFERROR(__xludf.DUMMYFUNCTION("""COMPUTED_VALUE"""),"César Augusto Schunck ") -> César Augusto Schunck | B42: =IFERROR(__xludf.DUMMYFUNCTION("""COMPUTED_VALUE"""),33435.0) -> 33435 | C42: =IFERROR(__xludf.DUMMYFUNCTION("""COMPUTED_VALUE"""),3.981722183E10) -> 39817221830
A43: =IFERROR(__xludf.DUMMYFUNCTION("""COMPUTED_VALUE"""),"Pedro Henrique dos Reis Schunck ") -> Pedro Henrique dos Reis Schunck | B43: =IFERROR(__xludf.DUMMYFUNCTION("""COMPUTED_VALUE"""),44092.0) -> 44092 | C43: =IFERROR(__xludf.DUMMYFUNCTION("""COMPUTED_VALUE"""),5.8817801836E10) -> 58817801836
A44: =IFERROR(__xludf.DUMMYFUNCTION("""COMPUTED_VALUE"""),"Alice Kraieb Ribeiro Schunck ") -> Alice Kraieb Ribeiro Schunck | B44: =IFERROR(__xludf.DUMMYFUNCTION("""COMPUTED_VALUE"""),40731.0) -> 40731 | C44: =IFERROR(__xludf.DUMMYFUNCTION("""COMPUTED_VALUE"""),5.6630404807E10) -> 56630404807
A45: =IFERROR(__xludf.DUMMYFUNCTION("""COMPUTED_VALUE"""),"Amanda Teixeira") -> Amanda Teixeira | B45: =IFERROR(__xludf.DUMMYFUNCTION("""COMPUTED_VALUE"""),38035.0) -> 38035 | C45: =IFERROR(__xludf.DUMMYFUNCTION("""COMPUTED_VALUE"""),4.1700389831E10) -> 41700389831
A46: =IFERROR(__xludf.DUMMYFUNCTION("""COMPUTED_VALUE"""),"Mateus Domingues Mendonça ") -> Mateus Domingues Mendonça | B46: =IFERROR(__xludf.DUMMYFUNCTION("""COMPUTED_VALUE"""),35675.0) -> 35675 | C46: =IFERROR(__xludf.DUMMYFUNCTION("""COMPUTED_VALUE"""),4.7685667827E10) -> 47685667827
A47: =IFERROR(__xludf.DUMMYFUNCTION("""COMPUTED_VALUE"""),"Ronaldo reis Mendonça ") -> Ronaldo reis Mendonça | B47: =IFERROR(__xludf.DUMMYFUNCTION("""COMPUTED_VALUE"""),24824.0) -> 24824 | C47: =IFERROR(__xludf.DUMMYFUNCTION("""COMPUTED_VALUE"""),1.0365189812E10) -> 10365189812
A48: =IFERROR(__xludf.DUMMYFUNCTION("""COMPUTED_VALUE"""),"Sonia Domingues Mendonça ") -> Sonia Domingues Mendonça | B48: =IFERROR(__xludf.DUMMYFUNCTION("""COMPUTED_VALUE"""),25096.0) -> 25096 | C48: =IFERROR(__xludf.DUMMYFUNCTION("""COMPUTED_VALUE"""),1.330976681E10) -> 13309766810
A49: =IFERROR(__xludf.DUMMYFUNCTION("""COMPUTED_VALUE"""),"Hullyanna Silva de Paula") -> Hullyanna Silva de Paula | B49: =IFERROR(__xludf.DUMMYFUNCTION("""COMPUTED_VALUE"""),35905.0) -> 35905 | C49: =IFERROR(__xludf.DUMMYFUNCTION("""COMPUTED_VALUE"""),4.5403296859E10) -> 45403296859
A50: =IFERROR(__xludf.DUMMYFUNCTION("""COMPUTED_VALUE"""),"Patricia Silva Pereira Marinho ") -> Patricia Silva Pereira Marinho | B50: =IFERROR(__xludf.DUMMYFUNCTION("""COMPUTED_VALUE"""),35419.0) -> 35419 | C50: =IFERROR(__xludf.DUMMYFUNCTION("""COMPUTED_VALUE"""),"444.282.958-63") -> 444.282.958-63
A51: =IFERROR(__xludf.DUMMYFUNCTION("""COMPUTED_VALUE"""),"Davi Silva Marinho") -> Davi Silva Marinho | B51: =IFERROR(__xludf.DUMMYFUNCTION("""COMPUTED_VALUE"""),45348.0) -> 45348 | C51: =IFERROR(__xludf.DUMMYFUNCTION("""COMPUTED_VALUE"""),"02401980857") -> 02401980857
A52: =IFERROR(__xludf.DUMMYFUNCTION("""COMPUTED_VALUE"""),"Guilherme Silva Pereira Marinho ") -> Guilherme Silva Pereira Marinho | B52: =IFERROR(__xludf.DUMMYFUNCTION("""COMPUTED_VALUE"""),35771.0) -> 35771 | C52: =IFERROR(__xludf.DUMMYFUNCTION("""COMPUTED_VALUE"""),"480.703.228-37") -> 480.703.228-37
A53: =IFERROR(__xludf.DUMMYFUNCTION("""COMPUTED_VALUE"""),"Hugo Luiz Guilherme ") -> Hugo Luiz Guilherme | B53: =IFERROR(__xludf.DUMMYFUNCTION("""COMPUTED_VALUE"""),35720.0) -> 35720 | C53: =IFERROR(__xludf.DUMMYFUNCTION("""COMPUTED_VALUE"""),4.5057408895E10) -> 45057408895
A54: =IFERROR(__xludf.DUMMYFUNCTION("""COMPUTED_VALUE"""),"Ana Beatriz Barbosa Cunha") -> Ana Beatriz Barbosa Cunha | B54: =IFERROR(__xludf.DUMMYFUNCTION("""COMPUTED_VALUE"""),35479.0) -> 35479 | C54: =IFERROR(__xludf.DUMMYFUNCTION("""COMPUTED_VALUE"""),"705.091.011-27") -> 705.091.011-27
A55: =IFERROR(__xludf.DUMMYFUNCTION("""COMPUTED_VALUE"""),"Jeferson goncalves de menezes") -> Jeferson goncalves de menezes | B55: =IFERROR(__xludf.DUMMYFUNCTION("""COMPUTED_VALUE"""),35969.0) -> 35969 | C55: =IFERROR(__xludf.DUMMYFUNCTION("""COMPUTED_VALUE"""),4.7485162837E10) -> 47485162837
A56: =IFERROR(__xludf.DUMMYFUNCTION("""COMPUTED_VALUE"""),"Carla Godinho Cardoso ") -> Carla Godinho Cardoso | B56: =IFERROR(__xludf.DUMMYFUNCTION("""COMPUTED_VALUE"""),30984.0) -> 30984 | C56: =IFERROR(__xludf.DUMMYFUNCTION("""COMPUTED_VALUE"""),3.150885386E9) -> 3150885386
A57: =IFERROR(__xludf.DUMMYFUNCTION("""COMPUTED_VALUE"""),"Victor Alexandre Farinassi") -> Victor Alexandre Farinassi | B57: =IFERROR(__xludf.DUMMYFUNCTION("""COMPUTED_VALUE"""),31318.0) -> 31318 | C57: =IFERROR(__xludf.DUMMYFUNCTION("""COMPUTED_VALUE"""),3.2760726886E10) -> 32760726886
A58: =IFERROR(__xludf.DUMMYFUNCTION("""COMPUTED_VALUE"""),"Aline Inacio Pimenta Correia") -> Aline Inacio Pimenta Correia | B58: =IFERROR(__xludf.DUMMYFUNCTION("""COMPUTED_VALUE"""),36186.0) -> 36186 | C58: =IFERROR(__xludf.DUMMYFUNCTION("""COMPUTED_VALUE"""),4.7539029862E10) -> 47539029862
A59: =IFERROR(__xludf.DUMMYFUNCTION("""COMPUTED_VALUE"""),"Vinicios Valério Lourenço ") -> Vinicios Valério Lourenço | B59: =IFERROR(__xludf.DUMMYFUNCTION("""COMPUTED_VALUE"""),31289.0) -> 31289 | C59: =IFERROR(__xludf.DUMMYFUNCTION("""COMPUTED_VALUE"""),3.613522381E10) -> 36135223810
A60: =IFERROR(__xludf.DUMMYFUNCTION("""COMPUTED_VALUE"""),"Thallita Ferreira da Silva ") -> Thallita Ferreira da Silva | B60: =IFERROR(__xludf.DUMMYFUNCTION("""COMPUTED_VALUE"""),35512.0) -> 35512 | C60: =IFERROR(__xludf.DUMMYFUNCTION("""COMPUTED_VALUE"""),4.7043988896E10) -> 47043988896
A61: =IFERROR(__xludf.DUMMYFUNCTION("""COMPUTED_VALUE"""),"Ismael Barbosa da Silva") -> Ismael Barbosa da Silva | B61: =IFERROR(__xludf.DUMMYFUNCTION("""COMPUTED_VALUE"""),31066.0) -> 31066 | C61: =IFERROR(__xludf.DUMMYFUNCTION("""COMPUTED_VALUE"""),"06460078408") -> 06460078408
A62: =IFERROR(__xludf.DUMMYFUNCTION("""COMPUTED_VALUE"""),"Raquel Morais Rangel Miyayaciki") -> Raquel Morais Rangel Miyayaciki | B62: =IFERROR(__xludf.DUMMYFUNCTION("""COMPUTED_VALUE"""),35105.0) -> 35105 | C62: =IFERROR(__xludf.DUMMYFUNCTION("""COMPUTED_VALUE"""),"444.021.548-39 ") -> 444.021.548-39
A63: =IFERROR(__xludf.DUMMYFUNCTION("""COMPUTED_VALUE"""),"Mauricio Takashi Miyayaciki ") -> Mauricio Takashi Miyayaciki | B63: =IFERROR(__xludf.DUMMYFUNCTION("""COMPUTED_VALUE"""),35348.0) -> 35348 | C63: =IFERROR(__xludf.DUMMYFUNCTION("""COMPUTED_VALUE"""),"457.916.688-48 ") -> 457.916.688-48
A64: =IFERROR(__xludf.DUMMYFUNCTION("""COMPUTED_VALUE"""),"Guilherme Cabral de Oliveira Passos ") -> Guilherme Cabral de Oliveira Passos | B64: =IFERROR(__xludf.DUMMYFUNCTION("""COMPUTED_VALUE"""),35278.0) -> 35278 | C64: =IFERROR(__xludf.DUMMYFUNCTION("""COMPUTED_VALUE"""),4.1279542802E10) -> 41279542802
A65: =IFERROR(__xludf.DUMMYFUNCTION("""COMPUTED_VALUE"""),"Tatiane da Silva Cabral Passos ") -> Tatiane da Silva Cabral Passos | B65: =IFERROR(__xludf.DUMMYFUNCTION("""COMPUTED_VALUE"""),35371.0) -> 35371 | C65: =IFERROR(__xludf.DUMMYFUNCTION("""COMPUTED_VALUE"""),4.3421905835E10) -> 43421905835
A66: =IFERROR(__xludf.DUMMYFUNCTION("""COMPUTED_VALUE"""),"Cecília Cabral Passos ") -> Cecília Cabral Passos | B66: =IFERROR(__xludf.DUMMYFUNCTION("""COMPUTED_VALUE"""),45594.0) -> 45594 | C66: =IFERROR(__xludf.DUMMYFUNCTION("""COMPUTED_VALUE"""),"06147309889") -> 06147309889
A67: =IFERROR(__xludf.DUMMYFUNCTION("""COMPUTED_VALUE"""),"Rosangela Holanda Rodrigues") -> Rosangela Holanda Rodrigues | B67: =IFERROR(__xludf.DUMMYFUNCTION("""COMPUTED_VALUE"""),21930.0) -> 21930 | C67: =IFERROR(__xludf.DUMMYFUNCTION("""COMPUTED_VALUE"""),"06913875835") -> 06913875835
A68: =IFERROR(__xludf.DUMMYFUNCTION("""COMPUTED_VALUE"""),"AMAILSON MATEUS DOS SANTOS DE JESUS") -> AMAILSON MATEUS DOS SANTOS DE JESUS | B68: =IFERROR(__xludf.DUMMYFUNCTION("""COMPUTED_VALUE"""),36191.0) -> 36191 | C68: =IFERROR(__xludf.DUMMYFUNCTION("""COMPUTED_VALUE"""),"119.417.089-78") -> 119.417.089-78
A69: =IFERROR(__xludf.DUMMYFUNCTION("""COMPUTED_VALUE"""),"Douglas De Souza Guerreiro") -> Douglas De Souza Guerreiro | B69: =IFERROR(__xludf.DUMMYFUNCTION("""COMPUTED_VALUE"""),31992.0) -> 31992 | C69: =IFERROR(__xludf.DUMMYFUNCTION("""COMPUTED_VALUE"""),"057.372.039-80") -> 057.372.039-80
A70: =IFERROR(__xludf.DUMMYFUNCTION("""COMPUTED_VALUE"""),"Daniel Sikora ") -> Daniel Sikora | B70: =IFERROR(__xludf.DUMMYFUNCTION("""COMPUTED_VALUE"""),28963.0) -> 28963 | C70: =IFERROR(__xludf.DUMMYFUNCTION("""COMPUTED_VALUE"""),"03586628935") -> 03586628935
A71: =IFERROR(__xludf.DUMMYFUNCTION("""COMPUTED_VALUE"""),"Adriano Pereira Xavier") -> Adriano Pereira Xavier | B71: =IFERROR(__xludf.DUMMYFUNCTION("""COMPUTED_VALUE"""),30505.0) -> 30505 | C71: =IFERROR(__xludf.DUMMYFUNCTION("""COMPUTED_VALUE"""),"04520613930") -> 04520613930
A72: =IFERROR(__xludf.DUMMYFUNCTION("""COMPUTED_VALUE"""),"Denise de Fatima dos Santos ") -> Denise de Fatima dos Santos | B72: =IFERROR(__xludf.DUMMYFUNCTION("""COMPUTED_VALUE"""),28507.0) -> 28507 | C72: =IFERROR(__xludf.DUMMYFUNCTION("""COMPUTED_VALUE"""),"02498362975") -> 02498362975
A73: =IFERROR(__xludf.DUMMYFUNCTION("""COMPUTED_VALUE"""),"Elisangela de amorim margarida") -> Elisangela de amorim margarida | B73: =IFERROR(__xludf.DUMMYFUNCTION("""COMPUTED_VALUE"""),26744.0) -> 26744 | C73: =IFERROR(__xludf.DUMMYFUNCTION("""COMPUTED_VALUE"""),"829.218.819-34 ") -> 829.218.819-34
A74: =IFERROR(__xludf.DUMMYFUNCTION("""COMPUTED_VALUE"""),"Lucas Andrade Oliveira") -> Lucas Andrade Oliveira | B74: =IFERROR(__xludf.DUMMYFUNCTION("""COMPUTED_VALUE"""),39824.0) -> 39824 | C74: =IFERROR(__xludf.DUMMYFUNCTION("""COMPUTED_VALUE"""),4.5312884839E10) -> 45312884839
A75: =IFERROR(__xludf.DUMMYFUNCTION("""COMPUTED_VALUE"""),"Heroic Gustavo Borges Monteiro ") -> Heroic Gustavo Borges Monteiro | B75: =IFERROR(__xludf.DUMMYFUNCTION("""COMPUTED_VALUE"""),34320.0) -> 34320 | C75: =IFERROR(__xludf.DUMMYFUNCTION("""COMPUTED_VALUE"""),"017.093.552-39") -> 017.093.552-39
A76: =IFERROR(__xludf.DUMMYFUNCTION("""COMPUTED_VALUE"""),"Daniela Pomin Selzelin Schuler") -> Daniela Pomin Selzelin Schuler | B76: =IFERROR(__xludf.DUMMYFUNCTION("""COMPUTED_VALUE"""),27246.0) -> 27246 | C76: =IFERROR(__xludf.DUMMYFUNCTION("""COMPUTED_VALUE"""),6.111914812E10) -> 61119148120
A77: =IFERROR(__xludf.DUMMYFUNCTION("""COMPUTED_VALUE"""),"Leonardo Munhoz Schuler") -> Leonardo Munhoz Schuler | B77: =IFERROR(__xludf.DUMMYFUNCTION("""COMPUTED_VALUE"""),29702.0) -> 29702 | C77: =IFERROR(__xludf.DUMMYFUNCTION("""COMPUTED_VALUE"""),2.9564339898E10) -> 29564339898
A78: =IFERROR(__xludf.DUMMYFUNCTION("""COMPUTED_VALUE"""),"Elisangela Souza Thomas ") -> Elisangela Souza Thomas | B78: =IFERROR(__xludf.DUMMYFUNCTION("""COMPUTED_VALUE"""),28941.0) -> 28941 | C78: =IFERROR(__xludf.DUMMYFUNCTION("""COMPUTED_VALUE"""),"701.774.211-77") -> 701.774.211-77
A79: =IFERROR(__xludf.DUMMYFUNCTION("""COMPUTED_VALUE"""),"Kenneth William thomas") -> Kenneth William thomas | B79: =IFERROR(__xludf.DUMMYFUNCTION("""COMPUTED_VALUE"""),40961.0) -> 40961 | C79: =IFERROR(__xludf.DUMMYFUNCTION("""COMPUTED_VALUE"""),"Nao") -> Nao
A80: =IFERROR(__xludf.DUMMYFUNCTION("""COMPUTED_VALUE"""),"Vera Lúcia Almeida souza") -> Vera Lúcia Almeida souza | B80: =IFERROR(__xludf.DUMMYFUNCTION("""COMPUTED_VALUE"""),17385.0) -> 17385 | C80: =IFERROR(__xludf.DUMMYFUNCTION("""COMPUTED_VALUE"""),"Nao") -> Nao
A81: =IFERROR(__xludf.DUMMYFUNCTION("""COMPUTED_VALUE"""),"Renata Aparecida de Oliveira Domingues Miranda ") -> Renata Aparecida de Oliveira Domingues Miranda | B81: =IFERROR(__xludf.DUMMYFUNCTION("""COMPUTED_VALUE"""),31669.0) -> 31669 | C81: =IFERROR(__xludf.DUMMYFUNCTION("""COMPUTED_VALUE"""),"348.932.358-00") -> 348.932.358-00
A82: =IFERROR(__xludf.DUMMYFUNCTION("""COMPUTED_VALUE"""),"Nara Jessica Nascimento Lacerda ") -> Nara Jessica Nascimento Lacerda | B82: =IFERROR(__xludf.DUMMYFUNCTION("""COMPUTED_VALUE"""),32640.0) -> 32640 | C82: =IFERROR(__xludf.DUMMYFUNCTION("""COMPUTED_VALUE"""),"03721439384") -> 03721439384
A83: =IFERROR(__xludf.DUMMYFUNCTION("""COMPUTED_VALUE"""),"Olinda Lima Soares") -> Olinda Lima Soares | B83: =IFERROR(__xludf.DUMMYFUNCTION("""COMPUTED_VALUE"""),28955.0) -> 28955 | C83: =IFERROR(__xludf.DUMMYFUNCTION("""COMPUTED_VALUE"""),9.7828661568E10) -> 97828661568
A84: =IFERROR(__xludf.DUMMYFUNCTION("""COMPUTED_VALUE"""),"Maria Luiza Gonçalves Domingos ") -> Maria Luiza Gonçalves Domingos | B84: =IFERROR(__xludf.DUMMYFUNCTION("""COMPUTED_VALUE"""),35170.0) -> 35170 | C84: =IFERROR(__xludf.DUMMYFUNCTION("""COMPUTED_VALUE"""),"03199406165") -> 03199406165
A85: =IFERROR(__xludf.DUMMYFUNCTION("""COMPUTED_VALUE"""),"Rafael Cristian de Mesquita Sato") -> Rafael Cristian de Mesquita Sato | B85: =IFERROR(__xludf.DUMMYFUNCTION("""COMPUTED_VALUE"""),34718.0) -> 34718 | C85: =IFERROR(__xludf.DUMMYFUNCTION("""COMPUTED_VALUE"""),4.1163819859E10) -> 41163819859
A86: =IFERROR(__xludf.DUMMYFUNCTION("""COMPUTED_VALUE"""),"Debora Garcia Galacine") -> Debora Garcia Galacine | B86: =IFERROR(__xludf.DUMMYFUNCTION("""COMPUTED_VALUE"""),36562.0) -> 36562 | C86: =IFERROR(__xludf.DUMMYFUNCTION("""COMPUTED_VALUE"""),"07360974305") -> 07360974305
A87: =IFERROR(__xludf.DUMMYFUNCTION("""COMPUTED_VALUE"""),"Francisca Rejane Gomes de Souza ") -> Francisca Rejane Gomes de Souza | B87: =IFERROR(__xludf.DUMMYFUNCTION("""COMPUTED_VALUE"""),31403.0) -> 31403 | C87: =IFERROR(__xludf.DUMMYFUNCTION("""COMPUTED_VALUE"""),3.7527969873E10) -> 37527969873
A88: =IFERROR(__xludf.DUMMYFUNCTION("""COMPUTED_VALUE"""),"Mirelly Souza de Goes ") -> Mirelly Souza de Goes | B88: =IFERROR(__xludf.DUMMYFUNCTION("""COMPUTED_VALUE"""),43825.0) -> 43825 | C88: =IFERROR(__xludf.DUMMYFUNCTION("""COMPUTED_VALUE"""),5.8059689835E10) -> 58059689835
A89: =IFERROR(__xludf.DUMMYFUNCTION("""COMPUTED_VALUE"""),"Gabriela Alves dos Reis Schunck") -> Gabriela Alves dos Reis Schunck | B89: =IFERROR(__xludf.DUMMYFUNCTION("""COMPUTED_VALUE"""),35893.0) -> 35893 | C89: =IFERROR(__xludf.DUMMYFUNCTION("""COMPUTED_VALUE"""),4.8060147889E10) -> 48060147889
A90: =IFERROR(__xludf.DUMMYFUNCTION("""COMPUTED_VALUE"""),"César Augusto Schunck ") -> César Augusto Schunck | B90: =IFERROR(__xludf.DUMMYFUNCTION("""COMPUTED_VALUE"""),33435.0) -> 33435 | C90: =IFERROR(__xludf.DUMMYFUNCTION("""COMPUTED_VALUE"""),3.981722183E10) -> 39817221830
A91: =IFERROR(__xludf.DUMMYFUNCTION("""COMPUTED_VALUE"""),"Carlos Eduardo Schunck dos Reis ") -> Carlos Eduardo Schunck dos Reis | B91: =IFERROR(__xludf.DUMMYFUNCTION("""COMPUTED_VALUE"""),41900.0) -> 41900 | C91: =IFERROR(__xludf.DUMMYFUNCTION("""COMPUTED_VALUE"""),4.8961840843E10) -> 48961840843
A92: =IFERROR(__xludf.DUMMYFUNCTION("""COMPUTED_VALUE"""),"Pedro Henrique dos Reis Schunck ") -> Pedro Henrique dos Reis Schunck | B92: =IFERROR(__xludf.DUMMYFUNCTION("""COMPUTED_VALUE"""),44092.0) -> 44092 | C92: =IFERROR(__xludf.DUMMYFUNCTION("""COMPUTED_VALUE"""),5.8817801836E10) -> 58817801836
A93: =IFERROR(__xludf.DUMMYFUNCTION("""COMPUTED_VALUE"""),"Alice Kraieb Ribeiro Schunck ") -> Alice Kraieb Ribeiro Schunck | B93: =IFERROR(__xludf.DUMMYFUNCTION("""COMPUTED_VALUE"""),40731.0) -> 40731 | C93: =IFERROR(__xludf.DUMMYFUNCTION("""COMPUTED_VALUE"""),5.6630404807E10) -> 56630404807
A94: =IFERROR(__xludf.DUMMYFUNCTION("""COMPUTED_VALUE"""),"Vinicius Costa Cabral ") -> Vinicius Costa Cabral | B94: =IFERROR(__xludf.DUMMYFUNCTION("""COMPUTED_VALUE"""),37300.0) -> 37300 | C94: =IFERROR(__xludf.DUMMYFUNCTION("""COMPUTED_VALUE"""),4.76304298E10) -> 47630429800
A95: =IFERROR(__xludf.DUMMYFUNCTION("""COMPUTED_VALUE"""),"Lucas Valentim Santos Vasconcelos ") -> Lucas Valentim Santos Vasconcelos | B95: =IFERROR(__xludf.DUMMYFUNCTION("""COMPUTED_VALUE"""),37474.0) -> 37474 | C95: =IFERROR(__xludf.DUMMYFUNCTION("""COMPUTED_VALUE"""),5.3892418861E10) -> 53892418861
A96: =IFERROR(__xludf.DUMMYFUNCTION("""COMPUTED_VALUE"""),"Vânia Aparecida Lopes Araujo ") -> Vânia Aparecida Lopes Araujo | B96: =IFERROR(__xludf.DUMMYFUNCTION("""COMPUTED_VALUE"""),28887.0) -> 28887 | C96: =IFERROR(__xludf.DUMMYFUNCTION("""COMPUTED_VALUE"""),"615.914.083-34 ") -> 615.914.083-34
A97: =IFERROR(__xludf.DUMMYFUNCTION("""COMPUTED_VALUE"""),"David Araujo da Silva ") -> David Araujo da Silva | B97: =IFERROR(__xludf.DUMMYFUNCTION("""COMPUTED_VALUE"""),31440.0) -> 31440 | C97: =IFERROR(__xludf.DUMMYFUNCTION("""COMPUTED_VALUE"""),1.1115698788E10) -> 11115698788
A98: =IFERROR(__xludf.DUMMYFUNCTION("""COMPUTED_VALUE"""),"Ana Talita Lopes Araujo ") -> Ana Talita Lopes Araujo | B98: =IFERROR(__xludf.DUMMYFUNCTION("""COMPUTED_VALUE"""),42594.0) -> 42594 | C98: =IFERROR(__xludf.DUMMYFUNCTION("""COMPUTED_VALUE"""),7.0747042292E10) -> 70747042292
A99: =IFERROR(__xludf.DUMMYFUNCTION("""COMPUTED_VALUE"""),"Nathan José Lopes Araujo ") -> Nathan José Lopes Araujo | B99: =IFERROR(__xludf.DUMMYFUNCTION("""COMPUTED_VALUE"""),44119.0) -> 44119 | C99: =IFERROR(__xludf.DUMMYFUNCTION("""COMPUTED_VALUE"""),"094.248.762-11 ") -> 094.248.762-11
A100: =IFERROR(__xludf.DUMMYFUNCTION("""COMPUTED_VALUE"""),"Ivone Rosa Soares Lopes ") -> Ivone Rosa Soares Lopes | B100: =IFERROR(__xludf.DUMMYFUNCTION("""COMPUTED_VALUE"""),20140.0) -> 20140 | C100: =IFERROR(__xludf.DUMMYFUNCTION("""COMPUTED_VALUE"""),"328.292.643-04") -> 328.292.643-04
...

Sheet CAIS LINS - SP
A1: DT SOLICITAÇÃO | B1: REQ | C1: DATA | D1: DE | E1: PARA | F1: SERVIDOR | G1: TELEFONE | H1: CPF | I1: DT NASC | J1: VALOR | K1: Custo | L1: Lucro | M1: PREV PGTO | N1: ENVIADO FATURAMENTO
A2: 45805 | B2: 15 | C2: 45810 | D2: LINS - SP | E2: SÃO PAULO - SP | F2: Amanda Ferreira de Oliveira Santos | G2: (14) 99831-5756 | H2: 400.638.988-45 | I2: 34137 | J2: =N$2 -> 174 | K2: 111.07 | M2: VALOR | N2: 174
A3: 45805 | B3: 16 | C3: 45811 | D3: SÃO PAULO - SP | E3: LINS - SP | F3: Amanda Ferreira de Oliveira Santos | G3: (14) 99831-5756 | H3: 400.638.988-45 | I3: 34137 | J3: =N$2 -> 174
A4: 45805 | B4: 17 | C4: 45810 | D4: LINS - SP | E4: SÃO PAULO - SP | F4: Eliana Barbosa Candido Camargo | G4: (14) 99677-3727 | H4: 61.824.448-43 | I4: 23886 | J4: =N$2 -> 174 | K4: 111.07
A5: 45805 | B5: 18 | C5: 45811 | D5: SÃO PAULO - SP | E5: LINS - SP | F5: Eliana Barbosa Candido Camargo | G5: (14) 99677-3727 | H5: 61.824.448-43 | I5: 23886 | J5: =N$2 -> 174
A6: 45824 | B6: 19 | C6: 45823 | D6: LINS - SP | E6: SÃO PAULO - SP | F6: SIMONE APARECIDA GAMA | G6: (14) 35331669 | H6: 277.423.148-51 | I6: 29124 | J6: =N$2 -> 174
A7: 45824 | B7: 20 | C7: 45824 | D7: SÃO PAULO - SP | E7: LINS - SP | F7: SIMONE APARECIDA GAMA | H7: - | I7: - | J7: =N$2 -> 174
A8: 45826 | B8: 21 | C8: 45832 | D8: LINS - SP | E8: SÃO PAULO - SP | F8: Vanessa da Silva Nascimento | J8: =N$2 -> 174
A9: 45831 | B9: 22 | C9: 45838 | D9: SÃO PAULO - SP | E9: LINS - SP | F9: RERISON BEZERRA CAMPOS | J9: =N$2 -> 174
A10: 45831 | B10: 23 | C10: 45837 | D10: LINS - SP | E10: SÃO PAULO - SP | F10: AMANDA FERREIRA DE OLIVIERA SANTOS | J10: =N$2 -> 174
A11: 45831 | B11: 24 | C11: 45837 | D11: LINS - SP | E11: SÃO PAULO - SP | F11: RERISON BEZERRA CAMPOS | J11: =N$2 -> 174
A12: 45831 | B12: 25 | C12: 45838 | D12: SÃO PAULO - SP | E12: LINS - SP | F12: AMANDA FERREIRA DE OLIVIERA SANTOS | H12: - | I12: - | J12: =N$2 -> 174
F13: TOTAL | J13: =SUM(J2:J12) -> 1914
A15: JULHO
A16: 45834 | B16: 26 | C16: 45839 | D16: LINS - SP | E16: SÃO PAULO - SP | F16: Bruna Rodrigues Gimenes Andrade | G16: (14) 35331669 | H16: 381.669.518-35 | I16: 33330 | J16: =N$2 -> 174
A17: 45834 | B17: 29 | C17: 45839 | D17: LINS - SP | E17: SÃO PAULO - SP | F17: Leda Simone dos Santos Lelis | G17: (14) 35331669 | H17: 110.629.958-21 | I17: 25629 | J17: =N$2 -> 174
A18: 45834 | B18: 27 | C18: 45840 | D18: SÃO PAULO - SP | E18: LINS - SP | F18: Bruna Rodrigues Gimenes Andrade | G18: (14) 35331669 | H18: 381.669.518-35 | I18: 33330 | J18: =N$2 -> 174
A19: 45834 | B19: 28 | C19: 45840 | D19: SÃO PAULO - SP | E19: LINS - SP | F19: Leda Simone dos Santos Lelis | G19: (14) 35331669 | H19: 110.629.958-21 | I19: 25629 | J19: =N$2 -> 174
F20: TOTAL | J20: =SUM(J16:J19) -> 696
A21: AGOSTO
A22: 45863 | B22: 30 | C22: - | D22: CANCELADA | E22: - | F22: - | J22: 0
A23: 45863 | B23: 31 | C23: - | D23: CANCELADA | E23: - | F23: - | J23: 0
A24: 45877 | B24: 32 | C24: 45877 | D24: LINS - SP | E24: JAU - SP | F24: Fábio José dos Santos | J24: =N$2 -> 174
A25: 45889 | B25: 33 | C25: 45893 | D25: LINS - SP | E25: SÃO PAULO - SP | F25: Amanda Ferreira de Oliveira Santos | J25: =N$2 -> 174
A26: 45889 | B26: 35 | C26: 45893 | D26: LINS - SP | E26: SÃO PAULO - SP | F26: Rérison Bezerra Campos | J26: =N$2 -> 174
A27: 45889 | B27: 34 | C27: 45894 | D27: SÃO PAULO - SP | E27: LINS - SP | F27: Amanda Ferreira de Oliveira Santos | J27: =N$2 -> 174
A28: 45889 | B28: 36 | C28: 45894 | D28: SÃO PAULO - SP | E28: LINS - SP | F28: Rérison Bezerra Campos | J28: =N$2 -> 174
F29: TOTAL | J29: =SUM(J22:J28) -> 870 | M29: Pago
A30: SETEMBRO
A31: 45923 | B31: 37 | C31: 45931 | D31: LINS - SP | E31: SÃO PAULO - SP | F31: ALEXANDRE FARIA VENTURA | J31: 174 | K31: 183.6
A32: 45923 | B32: 38 | C32: 45932 | D32: SÃO PAULO - SP | E32: LINS - SP | F32: ALEXANDRE FARIA VENTURA | J32: 174 | K32: 183.6 | M32: Pago
J34: =J32+(J32*0.2) -> 208.8
A36: FEVEIRO/2026 | M36: edpermanente.cflins@gmail.com
A37: 46066 | B37: 1 | C37: 46071 | D37: LINS - SP | E37: SÃO PAULO - SP | F37: Marcos Roberto Garcia Sales | J37: 174 | M37: RH CAIS Clemente Ferreira <rh-caisl@saude.sp.gov.br>
A38: 46066 | B38: 2 | C38: 46072 | D38: SÃO PAULO - SP | E38: LINS - SP | F38: Marcos Roberto Garcia Sales | J38: 174
J40: =J38+J37 -> 348 | M40: PAGO | N40: SIM

Sheet TJ VITORIA - ES
A1: DT SOLICITACAO | B1: CHECK IN | C1: CHECK OUT | D1: Nº DIARIAS | E1: COLABORADOR | F1: REFEICOES | G1: VLR DIARIA | H1: PREV VLR REFEICAO | I1: VLR TOTAL | J1: CUSTO HOSPEDAGEM | K1: CUSTO REFEIÇÂO | L1: CUSTO TT | M1: LUCRO | N1: PREV PGTO | O1: ENVIADO FATURAMENTO
A2: 45803 | B2: 45824 | C2: 45827 | D2: =IF(C2-B2=0,"",C2-B2) -> 3 | E2: ALICE BIANCHINI | F2: 4 | G2: =D2*O$3 -> 1109.61 | H2: =F2*O$4 -> 759.92 | I2: =G2+H2 -> 1869.53 | M2: SIM | N2: ATA | O2: 2025
A3: 45803 | B3: 45825 | C3: 45827 | D3: =IF(C3-B3=0,"",C3-B3) -> 2 | E3: LUCIANA LOPES ROCHA | F3: 3 | G3: =D3*O$3 -> 739.74 | H3: =F3*O$4 -> 569.94 | I3: =G3+H3 -> 1309.68 | M3: SIM | N3: DIARIA | O3: 369.87
A4: 45833 | B4: 45837 | C4: 45839 | D4: =IF(C4-B4=0,"",C4-B4) -> 2 | E4: EDILSON VITORELLI DINIZ LIMA | F4: 2 | G4: =D4*O$3 -> 739.74 | H4: =F4*O$4 -> 379.96 | I4: =G4+H4 -> 1119.7 | M4: SIM | N4: REFEICAO | O4: 189.98
D5: =IF(C5-B5=0,"",C5-B5) | H5: TOTAL | I5: =SUM(I2:I4) -> 4298.91
A9: 45845 | B9: 45853 | C9: 45854 | D9: =IF(C9-B9=0,"",C9-B9) -> 1 | E9: Rafael Alves Esteves | F9: 3 | G9: =D9*O$3 -> 369.87 | H9: =F9*O$4 -> 569.94 | I9: =G9+H9 -> 939.81 | J9: 551 | M9: SIM
A10: AGOSTO
A12: 45833 | B12: 45890 | C12: 45891 | D12: =IF(C12-B12=0,"",C12-B12) -> 1 | E12: Fredie de Souza Didier Junior | F12: =D12*2 -> 2 | G12: =D12*O$3 -> 369.87 | H12: =F12*O$4 -> 379.96 | I12: =G12+H12 -> 749.83 | J12: 331 | M12: SIM
A13: 45860 | B13: 45875 | C13: 45877 | D13: =IF(C13-B13=0,"",C13-B13) -> 2 | E13: Emily Karle dos Santos Conceição | F13: 2 | G13: =D13*O$3 -> 739.74 | H13: =F13*O$4 -> 379.96 | I13: =G13+H13 -> 1119.7 | J13: 1500 | M13: SIM
A14: 45860 | B14: 45876 | C14: 45878 | D14: =IF(C14-B14=0,"",C14-B14) -> 2 | E14: Miguel Fontes | F14: 1 | G14: =D14*O$3 -> 739.74 | H14: =F14*O$4 -> 189.98 | I14: =G14+H14 -> 929.72 | M14: SIM
A15: 45860 | B15: 45889 | C15: 45891 | D15: =IF(C15-B15=0,"",C15-B15) -> 2 | E15: Jair dos Santos Junior | F15: 3 | G15: =D15*O$3 -> 739.74 | H15: =F15*O$4 -> 569.94 | I15: =G15+H15 -> 1309.68 | M15: SIM
A16: 45860 | B16: 45890 | C16: 45893 | D16: =IF(C16-B16=0,"",C16-B16) -> 3 | E16: Marcelo Elias Naschenweng | F16: 0 | G16: 1312.9 | I16: 1109.61 | J16: 1312.9 | K16: 1109.61 | M16: SIM
A17: 45860 | B17: 45895 | C17: 45897 | D17: =IF(C17-B17=0,"",C17-B17) -> 2 | E17: Franklin Brasil Santos | F17: 3 | G17: =D17*O$3 -> 739.74 | H17: =F17*O$4 -> 569.94 | I17: =G17+H17 -> 1309.68 | M17: SIM
A18: 45860 | B18: 45897 | C18: 45899 | D18: =IF(C18-B18=0,"",C18-B18) -> 2 | E18: Rafael Guimarães | F18: 2 | G18: =D18*O$3 -> 739.74 | H18: =F18*O$4 -> 379.96 | I18: =G18+H18 -> 1119.7 | M18: SIM
A19: 45860 | B19: 45897 | C19: 45899 | D19: =IF(C19-B19=0,"",C19-B19) -> 2 | E19: Danilo Cunha Diniz | F19: 3 | G19: =D19*O$3 -> 739.74 | H19: =F19*O$4 -> 569.94 | I19: =G19+H19 -> 1309.68 | M19: SIM
A20: 45860 | B20: 45897 | C20: 45899 | D20: =IF(C20-B20=0,"",C20-B20) -> 2 | E20: Gilmar Silva Batista | F20: 3 | G20: =D20*O$3 -> 739.74 | H20: =F20*O$4 -> 569.94 | I20: =G20+H20 -> 1309.68 | M20: SIM
A21: 45860 | B21: 45897 | C21: 45899 | D21: =IF(C21-B21=0,"",C21-B21) -> 2 | E21: Marcos Vinicius Barroso | F21: 2 | G21: =D21*O$3 -> 739.74 | H21: =F21*O$4 -> 379.96 | I21: =G21+H21 -> 1119.7 | M21: SIM
A22: 45870 | B22: 45883 | C22: 45884 | D22: =IF(C22-B22=0,"",C22-B22) -> 1 | E22: Mauro da Fonseca Ellovitch | F22: 1 | G22: =D22*O$3 -> 369.87 | H22: =F22*O$4 -> 189.98 | I22: =G22+H22 -> 559.85 | M22: SIM
A23: 45882 | B23: 45891 | C23: 45892 | D23: =IF(C23-B23=0,"",C23-B23) -> 1 | E23: Felipe Soares Damous | F23: 1 | G23: =D23*O$3 -> 369.87 | H23: =F23*O$4 -> 189.98 | I23: =G23+H23 -> 559.85 | M23: SIM
G24: =SUM(H12:H23) -> 4369.54 | H24: TOTAL | I24: =SUM(I12:I23) -> 12506.68
A26: SETEMBRO
A27: 45908 | B27: 45909 | C27: 45910 | D27: =IF(C27-B27=0,"",C27-B27) -> 1 | E27: Renato Cidades Batista | F27: =D27*2 -> 2 | G27: =D27*O$3 -> 369.87 | H27: =(F27/2)*O$4 -> 189.98 | I27: =G27+H27 -> 559.85 | J27: 534 | M27: SIM
A28: 45908 | B28: 45912 | C28: 45913 | D28: =IF(C28-B28=0,"",C28-B28) -> 1 | E28: Márcia Campos Eurico | F28: =D28*2 -> 2 | G28: =D28*O$3 -> 369.87 | H28: =(F28/2)*O$4 -> 189.98 | I28: =G28+H28 -> 559.85 | J28: 399 | M28: SIM
A29: 45908 | B29: 45915 | C29: 45916 | D29: =IF(C29-B29=0,"",C29-B29) -> 1 | E29: Flávia Marciano Monteiro | F29: =D29*2 -> 2 | G29: =D29*O$3 -> 369.87 | H29: =(F29/2)*O$4 -> 189.98 | I29: =G29+H29 -> 559.85 | J29: 399 | M29: SIM
A30: 45922 | B30: 45952 | C30: 45954 | D30: =IF(C30-B30=0,"",C30-B30) -> 2 | E30: Paulo Rogério Bonini | F30: =D30*2 -> 4 | G30: =D30*O$3 -> 739.74 | H30: =F30*O$4 -> 759.92 | I30: =G30+H30 -> 1499.66 | J30: 694.55 | M30: SIM
A31: 45922 | B31: 45959 | C31: 45961 | D31: =IF(C31-B31=0,"",C31-B31) -> 2 | E31: Sebastião Luz Brito | F31: =D31*2 -> 4 | G31: =D31*O$3 -> 739.74 | H31: =F31*O$4 -> 759.92 | I31: =G31+H31 -> 1499.66 | J31: 694.55 | M31: SIM
A32: 45922 | B32: 45960 | C32: 45961 | D32: =IF(C32-B32=0,"",C32-B32) -> 1 | E32: Nelson Nery Junior | F32: =D32*2 -> 2 | G32: =D32*O$3 -> 369.87 | H32: =F32*O$4 -> 379.96 | I32: =G32+H32 -> 749.83 | J32: 378.97 | M32: SIM
D33: =IF(C33-B33=0,"",C33-B33) | G33: =D33*O$3 -> 0
A35: OUTUBRO
B36: 45945 | C36: 45948 | D36: =IF(C36-B36=0,"",C36-B36) -> 3 | E36: Fabrício Castagna Lunardi | F36: =D36*2 -> 6 | G36: =D36*O$3 -> 1109.61 | H36: =F36*O$4 -> 1139.88 | I36: =G36+H36 -> 2249.49
A38: NOVEMBRO
A40: 45968 | B40: 45974 | C40: 45976 | D40: =IF(C40-B40=0,"",C40-B40) -> 2 | E40: Beclaute Oliveira Silva | F40: 4 | G40: =D40*O$3 -> 739.74 | H40: =F40*O$4 -> 759.92 | I40: =G40+H40 -> 1499.66 | M40: SIM
A41: 45968 | B41: 45974 | C41: 45976 | D41: =IF(C41-B41=0,"",C41-B41) -> 2 | E41: Edilson Santana Gonçalves Filho | F41: =D41*2 -> 4 | G41: =D41*O$3 -> 739.74 | H41: =F41*O$4 -> 759.92 | I41: =G41+H41 -> 1499.66 | M41: SIM
A42: 45965 | B42: 45979 | C42: 45981 | D42: =IF(C42-B42=0,"",C42-B42) -> 2 | E42: José Rogério Cruz e Tucci | F42: =D42*2 -> 4 | G42: =D42*O$3 -> 739.74 | H42: =F42*O$4 -> 759.92 | I42: =G42+H42 -> 1499.66 | M42: SIM
A43: 45965 | B43: 45979 | C43: 45981 | D43: 1 | E43: Sérgio Luiz Kukina | F43: 0 | G43: =D43*O$3 -> 369.87 | H43: NO SHOW | I43: 369.87 | M43: SIM
A44: 45965 | B44: 45974 | C44: 45975 | D44: =IF(C44-B44=0,"",C44-B44) -> 1 | E44: Ana Paula Mota da Costa e Silva | F44: 2 | G44: =D44*O$3 -> 369.87 | H44: =F44*O$4 -> 379.96 | I44: =G44+H44 -> 749.83 | M44: SIM
H46: TOTAL | I46: =SUM(I40:I45) -> 5618.68
A47: DEZEMBRO
A48: 45988 | B48: 45995 | C48: 45997 | D48: =IF(C48-B48=0,"",C48-B48) -> 2 | E48: Ana Claudia Brandão de Barros Correia | F48: 2 | G48: =D48*O$3 -> 739.74 | H48: =F48*O$4 -> 379.96 | I48: =G48+H48 -> 1119.7 | M48: SIM
A49: 45965 | B49: 45994 | C49: 45998 | D49: =IF(C49-B49=0,"",C49-B49) -> 4 | E49: Eduardo Alvares de Carvalho | F49: 4 | G49: =D49*O$3 -> 1479.48 | H49: =F49*O$4 -> 759.92 | I49: =G49+H49 -> 2239.4 | M49: SIM
H50: TOTAL | I50: =SUM(I48:I49) -> 3359.1
A51: JANEIRO
A52: 46042 | B52: 46049 | C52: 46052 | D52: =IF(C52-B52=0,"",C52-B52) -> 3 | E52: José Faustino Macêdo de Souza Ferreira | F52: =D52*2 -> 6 | G52: =D52*O$3 -> 1109.61 | H52: =F52*O$4 -> 1139.88 | I52: =G52+H52 -> 2249.49
A53: 46042 | B53: 46049 | C53: 46052 | D53: =IF(C53-B53=0,"",C53-B53) -> 3 | E53: João Guilherme de Melo Peixoto | F53: =D53*2 -> 6 | G53: =D53*O$3 -> 1109.61 | H53: =F53*O$4 -> 1139.88 | I53: =G53+H53 -> 2249.49 | K53: 170
H54: TOTAL | I54: =SUM(I52:I53) -> 4498.98 | M54: SIM
A55: FEVEREIRO
A56: 46052 | B56: 46056 | C56: 46060 | D56: =IF(C56-B56=0,"",C56-B56) -> 4 | E56: JÉSSICA SILVA DA PAIXÃO | F56: 8 | G56: =D56*O$3 -> 1479.48 | H56: =F56*O$4 -> 1519.84 | I56: =G56+H56 -> 2999.32 | J56: 2192 | K56: 480 | L56: =SUM(J56:K56) -> 2672 | M56: =I56-L56 -> 327.32
A57: 46052 | B57: 46078 | C57: 46079 | D57: =IF(C57-B57=0,"",C57-B57) -> 1 | E57: PAULO ROGÉRIO BONIN | F57: =D57*2 -> 2 | G57: =D57*O$3 -> 369.87 | H57: =F57*O$4 -> 379.96 | I57: =G57+H57 -> 749.83 | J57: 548 | K57: 0 | L57: =SUM(J57:K57) -> 548 | M57: =I57-L57 -> 201.83
A58: 46084 | B58: 46081 | C58: 46084 | D58: =IF(C58-B58=0,"",C58-B58) -> 3 | E58: PATRÍCIA CENI | F58: =D58*2 -> 6 | G58: =D58*O$3 -> 1109.61 | H58: =F58*O$4 -> 1139.88 | I58: =G58+H58 -> 2249.49 | L58: =SUM(J58:K58) -> 0 | M58: =I58-L58 -> 2249.49
A59: 46084 | B59: 46084 | C59: 46092 | D59: =IF(C59-B59=0,"",C59-B59) -> 8 | E59: Arlindo da Silva Castro | F59: 14 | G59: =D59*O$3 -> 2958.96 | H59: =F59*O$4 -> 2659.72 | I59: =G59+H59 -> 5618.68 | L59: =SUM(J59:K59) -> 0 | M59: =I59-L59 -> 5618.68
A60: 46090 | B60: 46091 | C60: 46096 | D60: =IF(C60-B60=0,"",C60-B60) -> 5 | E60: FÁBIO WELLINGTON ATAÍDE ALVES | F60: 8 | G60: =D60*O$3 -> 1849.35 | H60: =F60*O$4 -> 1519.84 | I60: =G60+H60 -> 3369.19 | L60: =SUM(J60:K60) -> 0 | M60: =I60-L60 -> 3369.19
A61: 46090 | B61: 46091 | C61: 46095 | D61: =IF(C61-B61=0,"",C61-B61) -> 4 | E61: JOSEFA FRANCISCA DE AZEVEDO | F61: 7 | G61: =D61*O$3 -> 1479.48 | H61: =F61*O$4 -> 1329.86 | I61: =G61+H61 -> 2809.34 | L61: =SUM(J61:K61) -> 0 | M61: =I61-L61 -> 2809.34
A62: 46090 | B62: 46093 | C62: 46095 | D62: =IF(C62-B62=0,"",C62-B62) -> 2 | E62: Ministro SÉRGIO LUIZ KUKINA | F62: 0 | G62: =D62*O$3 -> 739.74 | H62: =F62*O$4 -> 0 | I62: =G62+H62 -> 739.74 | L62: =SUM(J62:K62) -> 0 | M62: =I62-L62 -> 739.74
A63: 46090 | B63: 46093 | C63: 46094 | D63: =IF(C63-B63=0,"",C63-B63) -> 1 | E63: Rodrigo Fontenelle | F63: =D63*2 -> 2 | G63: =D63*O$3 -> 369.87 | H63: =F63*O$4 -> 379.96 | I63: =G63+H63 -> 749.83 | L63: =SUM(J63:K63) -> 0 | M63: =I63-L63 -> 749.83
A64: 46090 | B64: 46100 | C64: 46102 | D64: =IF(C64-B64=0,"",C64-B64) -> 2 | E64: FÁBIO LUCAS DE ALBUQUERQUE LIMA | F64: 3 | G64: =D64*O$3 -> 739.74 | H64: =F64*O$4 -> 569.94 | I64: =G64+H64 -> 1309.68 | L64: =SUM(J64:K64) -> 0 | M64: =I64-L64 -> 1309.68
A65: 46090 | B65: 46107 | C65: 46108 | D65: =IF(C65-B65=0,"",C65-B65) -> 1 | E65: FLÁVIA DA COSTA VIANA | F65: =D65*2 -> 2 | G65: =D65*O$3 -> 369.87 | H65: =F65*O$4 -> 379.96 | I65: =G65+H65 -> 749.83 | L65: =SUM(J65:K65) -> 0 | M65: =I65-L65 -> 749.83
A66: 46092 | B66: 46106 | C66: 46108 | D66: =IF(C66-B66=0,"",C66-B66) -> 2 | E66: ANA CLAUDIA BRANDAO DE BARROS CORREIA | F66: 3 | G66: =D66*O$3 -> 739.74 | H66: =F66*O$4 -> 569.94 | I66: =G66+H66 -> 1309.68 | L66: =SUM(J66:K66) -> 0 | M66: =I66-L66 -> 1309.68
A67: 46092 | B67: 46106 | C67: 46109 | D67: =IF(C67-B67=0,"",C67-B67) -> 3 | E67: Eduardo carvalho | F67: 5 | G67: =D67*O$3 -> 1109.61 | H67: =F67*O$4 -> 949.9 | I67: =G67+H67 -> 2059.51 | L67: =SUM(J67:K67) -> 0 | M67: =I67-L67 -> 2059.51
A68: 46092 | B68: 46107 | C68: 46109 | D68: =IF(C68-B68=0,"",C68-B68) -> 2 | E68: Eliane Cristina Martins de Resende | F68: 3 | G68: =D68*O$3 -> 739.74 | H68: =F68*O$4 -> 569.94 | I68: =G68+H68 -> 1309.68 | L68: =SUM(J68:K68) -> 0 | M68: =I68-L68 -> 1309.68
H70: TOTAL | I70: =SUM(I56:I68) -> 26023.8
A71: ABRIL
A72: 46108 | B72: 46121 | C72: 46123 | D72: =IF(C72-B72=0,"",C72-B72) -> 2 | E72: Mário Goulart Maia | F72: =D72*2 -> 4 | G72: =D72*O$3 -> 739.74 | H72: =F72*O$4 -> 759.92 | I72: =G72+H72 -> 1499.66 | J72: 1266.3 | L72: =SUM(J72:K72) -> 1266.3 | M72: =I72-L72 -> 233.36
A73: 46108 | B73: 46121 | C73: 46123 | D73: =IF(C73-B73=0,"",C73-B73) -> 2 | E73: Viviane Landin | F73: 6 | G73: =D73*O$3 -> 739.74 | H73: =F73*O$4 -> 1139.88 | I73: =G73+H73 -> 1879.62 | J73: 1266.3 | L73: =SUM(J73:K73) -> 1266.3 | M73: =I73-L73 -> 613.32
A74: 46108 | B74: 46138 | C74: 46140 | D74: =IF(C74-B74=0,"",C74-B74) -> 2 | E74: Dr. Alexandre Abrahão | F74: 5 | G74: =D74*O$3 -> 739.74 | H74: =F74*O$4 -> 949.9 | I74: =G74+H74 -> 1689.64 | J74: 945 | L74: =SUM(J74:K74) -> 945 | M74: =I74-L74 -> 744.64
A75: 46108 | B75: 46138 | C75: 46140 | D75: =IF(C75-B75=0,"",C75-B75) -> 2 | E75: Ivana David | F75: =D75*2 -> 4 | G75: =D75*O$3 -> 739.74 | H75: =F75*O$4 -> 759.92 | I75: =G75+H75 -> 1499.66 | J75: 945 | L75: =SUM(J75:K75) -> 945 | M75: =I75-L75 -> 554.66
A76: 46108 | B76: 46126 | C76: 46129 | D76: =IF(C76-B76=0,"",C76-B76) -> 3 | E76: Denise Duarte Bruno | F76: 5 | G76: =D76*O$3 -> 1109.61 | H76: =F76*O$4 -> 949.9 | I76: =G76+H76 -> 2059.51 | J76: 1417.5 | L76: =SUM(J76:K76) -> 1417.5 | M76: =I76-L76 -> 642.01
A77: 46126 | B77: 46135 | C77: 46137 | D77: =IF(C77-B77=0,"",C77-B77) -> 2 | E77: Herbert William Ramos | F77: 4 | G77: =D77*O$3 -> 739.74 | H77: =F77*O$4 -> 759.92 | I77: =G77+H77 -> 1499.66 | J77: 945
H79: TOTAL | I79: =SUM(I72:I77) -> 10127.75 | M79: =SUM(M72:M76) -> 2787.99 | N79: PAGO | O79: SIM
A80: MAIO
A81: 46122 | B81: 0 | C81: 0 | D81: 0 | E81: Dra Camila Varela | F81: 1 | G81: =D81*O$3 -> 0 | H81: =F81*O$4 -> 189.98 | I81: =G81+H81 -> 189.98 | K81: 99 | L81: =SUM(K81+J81) -> 99 | M81: =I81-L81 -> 90.98
A82: 46141 | B82: 46146 | C82: 46148 | D82: =IF(C82-B82=0,"",C82-B82) -> 2 | E82: ANA CLAUDIA BRANDÃO DE BARROS CORREIA | F82: =D82*2 -> 4 | G82: =D82*O$3 -> 739.74 | H82: =F82*O$4 -> 759.92 | I82: =G82+H82 -> 1499.66 | J82: 1171.8 | K82: 77 | L82: =SUM(K82+J82) -> 1248.8 | M82: =I82-L82 -> 250.86
A83: 46141 | B83: 46146 | C83: 46147 | D83: 1 | E83: DR. CLÊNIO SCHULZE | F83: 0 | G83: =D83*O$3 -> 369.87 | H83: =F83*O$4 -> 0 | I83: =G83+H83 -> 369.87 | J83: 438 | L83: =SUM(K83+J83) -> 438 | M83: =I83-L83 -> -68.13
A84: 46141 | B84: 46149 | C84: 46150 | D84: =IF(C84-B84=0,"",C84-B84) -> 1 | E84: Dr. Alexandre Flexa | F84: 0 | G84: =D84*O$3 -> 369.87 | H84: =F84*O$4 -> 0 | I84: =G84+H84 -> 369.87 | J84: 585.9 | L84: =SUM(K84+J84) -> 585.9 | M84: =I84-L84 -> -216.03
A85: 46141 | B85: 46149 | C85: 46150 | D85: =IF(C85-B85=0,"",C85-B85) -> 1 | E85: Dra. Patrícia Corrêa Sanches Lamosa | F85: =D85*2 -> 2 | G85: =D85*O$3 -> 369.87 | H85: =F85*O$4 -> 379.96 | I85: =G85+H85 -> 749.83 | J85: 585.9 | L85: =SUM(K85+J85) -> 585.9 | M85: =I85-L85 -> 163.93
A86: 46141 | B86: 46161 | C86: 46163 | D86: =IF(C86-B86=0,"",C86-B86) -> 2 | E86: Volgane Oliveira Carvalho | F86: =D86*2 -> 4 | G86: =D86*O$3 -> 739.74 | H86: =F86*O$4 -> 759.92 | I86: =G86+H86 -> 1499.66 | J86: 973.36 | L86: =SUM(K86+J86) -> 973.36 | M86: =I86-L86 -> 526.3
A87: 46141 | B87: 46163 | C87: 46165 | D87: =IF(C87-B87=0,"",C87-B87) -> 2 | E87: Márcia Maria Borba Lins | F87: =D87*2 -> 4 | G87: =D87*O$3 -> 739.74 | H87: =F87*O$4 -> 759.92 | I87: =G87+H87 -> 1499.66 | J87: 973.36 | L87: =SUM(K87+J87) -> 973.36 | M87: =I87-L87 -> 526.3
A88: 46141 | B88: 46163 | C88: 46165 | D88: =IF(C88-B88=0,"",C88-B88) -> 2 | E88: Reginaldo Torres Alves Jr. | F88: =D88*2 -> 4 | G88: =D88*O$3 -> 739.74 | H88: =F88*O$4 -> 759.92 | I88: =G88+H88 -> 1499.66 | J88: 973.36 | L88: =SUM(K88+J88) -> 973.36 | M88: =I88-L88 -> 526.3
A89: 46141 | B89: 46166 | C89: 46167 | D89: 0 | E89: Wanira Oliveira de Albuquerque | F89: =D89*2 -> 0 | G89: =D89*O$3 -> 0 | H89: =F89*O$4 -> 0 | I89: =G89+H89 -> 0 | J89: 486.68 | L89: =SUM(K89+J89) -> 486.68 | M89: =I89-L89 -> -486.68
H92: TOTAL | I92: =SUM(I81:I90) -> 7678.19 | M92: =SUM(M81:M89) -> 1313.83

Sheet COREN -MA
A1: DATA SOLICITACAO | B1: MODELO DE VEICULO | C1: PLACA | D1: SAIDA | E1: DATA | F1: COLABORADOR | G1: CPF | H1: DT NASCIMENTO | I1: VALOR | J1: CUSTO | K1: LUCRO | L1: PREV PGTO | M1: ENVIADO FATURAMENTO
A2: 45818 | B2: FRONTIER | C2: NUJ 9C55 | D2: PONTA DA ESPERA | E2: 45824 | F2: LOUREDIR CANTANHEDE | G2: 02919330330 | H2: 31721 | I2: =IF(C2<>"-",O$3,O$2) -> 481.76 | J2: 143 | K2: =I2-J2 -> 338.76 | N2: VLR PEDESTRE | O2: 32.12
A3: 45818 | B3: - | C3: - | D3: PONTA DA ESPERA | E3: 45824 | F3: Milene Barreto Brito | G3: 816.436.243-34 | H3: 28861 | I3: =IF(C3<>"-",O$3,O$2) -> 32.12 | J3: 11 | K3: =I3-J3 -> 21.12 | N3: VLR CARRO | O3: 481.76
A4: 45818 | B4: FRONTIER | C4: NUJ 9C55 | D4: CUJUPE | E4: 45828 | F4: LOUREDIR CANTANHEDE | G4: 02919330330 | H4: 31721 | I4: =IF(C4<>"-",O$3,O$2) -> 481.76 | J4: 143 | K4: =I4-J4 -> 338.76
A5: 45818 | B5: - | C5: - | D5: CUJUPE | E5: 45828 | F5: Milene Barreto Brito | G5: 816.436.243-34 | H5: 28861 | I5: =IF(C5<>"-",O$3,O$2) -> 32.12 | J5: 11 | K5: =I5-J5 -> 21.12
A6: 45825 | B6: FRONTIER | C6: NUJ 9C55 | D6: PONTA DA ESPERA | E6: 23/062025 | F6: BEATRIZ ALMEIDA | G6: 771.508.483-20 | H6: 28042 | I6: =IF(C6<>"-",O$3,O$2) -> 481.76 | J6: 143 | K6: =I6-J6 -> 338.76 | N6: emails
A7: 45825 | B7: - | C7: - | D7: PONTA DA ESPERA | E7: 23/062025 | F7: CASSIA CHAVES LOPES | G7: 017.528.303-69 | H7: 31594 | I7: =IF(C7<>"-",O$3,O$2) -> 32.12 | J7: 11 | K7: =I7-J7 -> 21.12 | N7: \ | O7: administracao@corenma.gov.br>, controladoria@corenma.gov.br <controladoria@corenma.gov.br>
A8: 45831 | B8: FRONTIER | C8: NUJ 9C55 | D8: PONTA DA ESPERA | E8: 45833 | F8: JONATHAN SILVA DOS SANTOS CAMPOS | G8: 056.907.183-60 | H8: 33666 | I8: =IF(C8<>"-",O$3,O$2) -> 481.76 | J8: 143 | K8: =I8-J8 -> 338.76 | O8: Gestão de Contratos
A9: 45831 | B9: - | C9: - | D9: PONTA DA ESPERA | E9: 45833 | F9: MARINA APOLONIO DE BARROS COSTA | G9: 001.818.263-13 | H9: 32675 | I9: =IF(C9<>"-",O$3,O$2) -> 32.12 | J9: 11 | K9: =I9-J9 -> 21.12 | O9: <gestaodecontratos@corenma.gov.br>
A10: 45831 | B10: - | C10: - | D10: PONTA DA ESPERA | E10: 45833 | F10: JAIRO MUNIZ DA SILVA | G10: 036.470.663-54 | H10: 33071 | I10: =IF(C10<>"-",O$3,O$2) -> 32.12 | J10: 11 | K10: =I10-J10 -> 21.12
A11: 45831 | B11: FRONTIER | C11: NUJ 9C55 | D11: CUJUPE | E11: 45835 | F11: JONATHAN SILVA DOS SANTOS CAMPOS | G11: 056.907.183-60 | H11: 33666 | I11: =IF(C11<>"-",O$3,O$2) -> 481.76 | J11: 143 | K11: =I11-J11 -> 338.76
A12: 45831 | B12: - | C12: - | D12: CUJUPE | E12: 45835 | F12: MARINA APOLONIO DE BARROS COSTA | G12: 001.818.263-13 | H12: 32675 | I12: =IF(C12<>"-",O$3,O$2) -> 32.12 | J12: 11 | K12: =I12-J12 -> 21.12
A13: 45831 | B13: - | C13: - | D13: CUJUPE | E13: 45835 | F13: JAIRO MUNIZ DA SILVA | G13: 036.470.663-54 | H13: 33071 | I13: =IF(C13<>"-",O$3,O$2) -> 32.12 | J13: 11 | K13: =I13-J13 -> 21.12
H14: TOTAL | I14: =SUM(I2:I13) -> 2633.64 | J14: =SUM(J2:J13) -> 792 | K14: =SUM(K2:K13) -> 1841.64 | L14: PAGO | M14: SIM
A15: JULHO
A16: 45840 | B16: - | C16: - | D16: CUJUPE | E16: 45854 | F16: LOUREDIR CANTANHEDE | G16: 02919330330 | H16: 31721 | I16: =IF(C16<>"-",O$3,O$2) -> 32.12 | J16: 11 | K16: =I16-J16 -> 21.12
A17: 45854 | B17: TIGGO 5X | C17: ROD 9C57 | D17: CUJUPE | E17: 45854 | F17: LOUREDIR CANTANHEDE | G17: 02919330330 | H17: 31721 | I17: =IF(C17<>"-",O$3,O$2) -> 481.76 | J17: 143 | K17: =I17-J17 -> 338.76
A18: 45854 | B18: TIGGO 5X | C18: ROD 9C57 | D18: PONTA DA ESPERA | E18: 45865 | F18: LOUREDIR CANTANHEDE | G18: 02919330330 | H18: 31721 | I18: =IF(C18<>"-",O$3,O$2) -> 481.76 | J18: 143 | K18: =I18-J18 -> 338.76
A19: 45840 | B19: - | C19: - | D19: PONTA DA ESPERA | E19: 45857 | F19: LOUREDIR CANTANHEDE | G19: 02919330330 | H19: 31721 | I19: =IF(C19<>"-",O$3,O$2) -> 32.12 | J19: 11 | K19: =I19-J19 -> 21.12
H21: TOTAL | I21: =SUM(I$16:I20) -> 1027.76 | J21: =SUM(J$16:J20) -> 308 | K21: =SUM(K$16:K20) -> 719.76 | L21: PAGO | M21: SIM
A22: AGOSTO
A23: 45876 | B23: TIGGO 5X | C23: ROD 9C57 | D23: CUJUPE | F23: LOUREDIR CANTANHEDE | G23: 02919330330 | H23: 31721 | I23: =IF(C23<>"-",O$3,O$2) -> 481.76 | J23: 143 | K23: =I23-J23 -> 338.76
A24: 45876 | B24: TIGGO 5X | C24: ROD 9C57 | D24: PONTA DA ESPERA | F24: LOUREDIR CANTANHEDE | G24: 02919330330 | H24: 31721 | I24: =IF(C24<>"-",O$3,O$2) -> 481.76 | J24: 143 | K24: =I24-J24 -> 338.76
H25: TOTAL | I25: =SUM(I$23:I24) -> 963.52 | J25: =SUM(J$23:J24) -> 286 | K25: =SUM(K$23:K24) -> 677.52 | L25: PAGO | M25: SIM | N25: OK
A26: SETEMBRO
A27: 45903 | B27: TIGGO 5X | C27: ROD 9C57 | D27: CUJUPE | E27: 45915 | F27: LOUREDIR CANTANHEDE | G27: 02919330330 | H27: 31721 | I27: =IF(C27<>"-",O$3,O$2) -> 481.76 | J27: 143 | K27: =I27-J27 -> 338.76
A28: 45903 | B28: TIGGO 5X | C28: ROD 9C57 | D28: PONTA DA ESPERA | E28: 45918 | F28: LOUREDIR CANTANHEDE | G28: 02919330330 | H28: 31721 | I28: =IF(C28<>"-",O$3,O$2) -> 481.76 | J28: 143 | K28: =I28-J28 -> 338.76
A29: 45903 | B29: FRONTIER | C29: NUJ 9C55 | D29: PONTA DA ESPERA | E29: 45922 | F29: LOUREDIR CANTANHEDE | G29: 02919330330 | H29: 31721 | I29: =IF(C29<>"-",O$3,O$2) -> 481.76 | J29: 143 | K29: =I29-J29 -> 338.76
A30: 45903 | B30: FRONTIER | C30: NUJ 9C55 | D30: PONTA DA ESPERA | E30: 45926 | F30: LOUREDIR CANTANHEDE | G30: 02919330330 | H30: 31721 | I30: =IF(C30<>"-",O$3,O$2) -> 481.76 | J30: 143 | K30: =I30-J30 -> 338.76
A31: 45903 | B31: - | C31: - | D31: PONTA DA ESPERA | E31: 45922 | F31: MILENE BARRETO BRITO | G31: 816.436.243-34 | H31: 28861 | I31: =IF(C31<>"-",O$3,O$2) -> 32.12 | J31: 11 | K31: =I31-J31 -> 21.12
A32: 45903 | B32: - | C32: - | D32: PONTA DA ESPERA | E32: 45926 | F32: MILENE BARRETO BRITO | G32: 816.436.243-34 | H32: 28861 | I32: =IF(C32<>"-",O$3,O$2) -> 32.12 | J32: 11 | K32: =I32-J32 -> 21.12
H34: TOTAL | I34: =SUM(I$27:I33) -> 1991.28 | J34: =SUM(J$27:J33) -> 594 | K34: =SUM(K$27:K33) -> 1397.28 | L34: PAGO | M34: SIM | N34: ok
A35: NOVEMBRO
A36: 45967 | B36: FRONTIER | C36: NUJ 9C55 | D36: PONTA DA ESPERA | E36: 45978 | F36: LOUREDIR CANTANHEDE | G36: 02919330330 | H36: 31721 | I36: =IF(C36<>"-",O$3,O$2) -> 481.76 | J36: 153 | K36: =I36-J36 -> 328.76
A37: 45967 | B37: - | C37: - | D37: PONTA DA ESPERA | E37: 45978 | F37: Milene Barreto Brito | G37: 816.436.243-34 | H37: 28861 | I37: =IF(C37<>"-",O$3,O$2) -> 32.12 | J37: 11 | K37: =I37-J37 -> 21.12
A38: 45967 | B38: FRONTIER | C38: NUJ 9C55 | D38: CUJUPE | E38: 45982 | F38: LOUREDIR CANTANHEDE | G38: 02919330330 | H38: 31721 | I38: =IF(C38<>"-",O$3,O$2) -> 481.76 | J38: 153 | K38: =I38-J38 -> 328.76
A39: 45967 | B39: - | C39: - | D39: CUJUPE | E39: 45982 | F39: Milene Barreto Brito | G39: 816.436.243-34 | H39: 28861 | I39: =IF(C39<>"-",O$3,O$2) -> 32.12 | J39: 11 | K39: =I39-J39 -> 21.12
H41: TOTAL | I41: =SUM(I$36:I40) -> 1027.76 | J41: =SUM(J$36:J40) -> 328 | K41: =SUM(K$36:K40) -> 699.76 | L41: PAGO | M41: SIM
A42: DEZEMBRO
A43: 45989 | B43: TIGGO 5X | C43: ROD 9C57 | D43: CUJUPE | E43: 46006 | F43: LOUREDIR CANTANHEDE | G43: 02919330330 | H43: 31721 | I43: =IF(C43<>"-",O$3,O$2) -> 481.76 | J43: 153 | K43: =I43-J43 -> 328.76
A44: 45989 | B44: TIGGO 5X | C44: ROD 9C57 | D44: PONTA DA ESPERA | E44: 46009 | F44: LOUREDIR CANTANHEDE | G44: 02919330330 | H44: 31721 | I44: =IF(C44<>"-",O$3,O$2) -> 481.76 | J44: 153 | K44: =I44-J44 -> 328.76
A45: 45989 | B45: FRONTIER | C45: NUJ 9C55 | D45: PONTA DA ESPERA | E45: 45926 | F45: LOUREDIR CANTANHEDE | G45: 02919330330 | H45: 31721 | I45: =IF(C45<>"-",O$3,O$2) -> 481.76 | J45: 140 | K45: =I45-J45 -> 341.76
A46: 45989 | B46: - | C46: - | D46: PONTA DA ESPERA | E46: 45922 | F46: MILENE BARRETO BRITO | G46: 816.436.243-34 | H46: 28861 | I46: =IF(C46<>"-",O$3,O$2) -> 32.12 | J46: 10 | K46: =I46-J46 -> 22.12 | L46: PAGO | M46: SIM
H47: TOTAL | I47: =SUM(I43:I46) -> 1477.4 | J47: =SUM(J43:J46) -> 456 | K47: =SUM(K43:K46) -> 1021.4
A48: JANEIRO
A49: 46028 | B49: TIGGO 5X | C49: ROD 9C57 | D49: CUJUPE | E49: 46034 | F49: LOUREDIR CANTANHEDE | G49: 02919330330 | H49: 31721 | I49: =IF(C49<>"-",O$3,O$2) -> 481.76 | J49: 153 | K49: =I49-J49 -> 328.76
A50: 46028 | B50: TIGGO 5X | C50: ROD 9C57 | D50: PONTA DA ESPERA | E50: 46036 | F50: LOUREDIR CANTANHEDE | G50: 02919330330 | H50: 31721 | I50: =IF(C50<>"-",O$3,O$2) -> 481.76 | J50: 153 | K50: =I50-J50 -> 328.76
A51: 46043 | B51: TIGGO 5X | C51: ROD 9C57 | D51: CUJUPE | E51: 46056 | F51: LOUREDIR CANTANHEDE | G51: 02919330330 | H51: 31721 | I51: =IF(C51<>"-",O$3,O$2) -> 481.76 | J51: 153 | K51: =I51-J51 -> 328.76
A52: 46043 | B52: TIGGO 5X | C52: ROD 9C57 | D52: PONTA DA ESPERA | E52: 46058 | F52: LOUREDIR CANTANHEDE | G52: 02919330330 | H52: 31721 | I52: =IF(C52<>"-",O$3,O$2) -> 481.76 | J52: 153 | K52: =I52-J52 -> 328.76
A53: 46051 | B53: FRONTIER | C53: NUJ 9C55 | D53: CUJUPE | E53: 46052 | F53: Deusdede | G53: 620.782.241-20 | I53: =IF(C53<>"-",O$3,O$2) -> 481.76 | J53: 153 | K53: =I53-J53 -> 328.76
A54: 46051 | B54: - | C54: - | D54: CUJUPE | E54: 46052 | F54: Telciane Martins Feitosa Rios | G54: 035.213.903-06 | H54: 32888 | I54: =IF(C54<>"-",O$3,O$2) -> 32.12 | J54: 10 | K54: =I54-J54 -> 22.12
A55: 46051 | B55: - | C55: - | D55: CUJUPE | E55: 46052 | F55: Nelciane Mesquita Pinheiro | G55: 025.214.993-90 | H55: 31777 | I55: =IF(C55<>"-",O$3,O$2) -> 32.12 | J55: 10 | K55: =I55-J55 -> 22.12
A56: 46051 | B56: - | C56: - | D56: CUJUPE | E56: 46052 | F56: Maria Jose Gomes | G56: 281.388.213-53 | H56: 23830 | I56: =IF(C56<>"-",O$3,O$2) -> 32.12 | J56: 10 | K56: =I56-J56 -> 22.12
H57: TOTAL | I57: =SUM(I49:I56) -> 2505.16 | J57: =SUM(J49:J56) -> 795 | K57: =SUM(K49:K56) -> 1710.16 | L57: PAGO | M57: SIM
A58: FEVEREIRO, MARCO e ABRIL
A59: 46086 | B59: TIGGO 5X | C59: ROD 9C57 | D59: CUJUPE | E59: 46090 | F59: LOUREDIR CANTANHEDE | G59: 02919330330 | H59: 31721 | I59: =IF(C59<>"-",O$3,O$2) -> 481.76 | J59: 153 | K59: =I59-J59 -> 328.76
A60: 46086 | B60: TIGGO 5X | C60: ROD 9C57 | D60: PONTA DA ESPERA | E60: 46093 | F60: LOUREDIR CANTANHEDE | G60: 02919330330 | H60: 31721 | I60: =IF(C60<>"-",O$3,O$2) -> 481.76 | J60: 153 | K60: =I60-J60 -> 328.76
A61: 46112 | B61: TIGGO 5X | C61: ROD 9C57 | D61: CUJUPE | E61: 46119 | F61: LOUREDIR CANTANHEDE | G61: 02919330330 | H61: 31721 | I61: =IF(C61<>"-",O$3,O$2) -> 481.76 | J61: 230 | K61: =I61-J61 -> 251.76
A62: 46112 | B62: TIGGO 5X | C62: ROD 9C57 | D62: PONTA DA ESPERA | E62: 46122 | F62: LOUREDIR CANTANHEDE | G62: 02919330330 | H62: 31721 | I62: =IF(C62<>"-",O$3,O$2) -> 481.76 | J62: 141 | K62: =I62-J62 -> 340.76
A63: 46129 | B63: TIGGO 5X | C63: ROD 9C57 | D63: CUJUPE | E63: 46133 | F63: LOUREDIR CANTANHEDE | G63: 02919330330 | H63: 31721 | I63: =IF(C63<>"-",O$3,O$2) -> 481.76 | J63: 230
A64: 46129 | B64: TIGGO 5X | C64: ROD 9C57 | D64: PONTA DA ESPERA | E64: 46136 | F64: LOUREDIR CANTANHEDE | G64: 02919330330 | H64: 31721 | I64: =IF(C64<>"-",O$3,O$2) -> 481.76 | J64: 143
A65: 46129 | B65: FRONTIER | C65: ROD 9C57 | D65: PONTA DA ESPERA | E65: 46139 | F65: LOUREDIR CANTANHEDE | G65: 02919330330 | H65: 31721 | I65: =IF(C65<>"-",O$3,O$2) -> 481.76 | J65: 200
A66: 46129 | B66: - | C66: - | D66: PONTA DA ESPERA | E66: 46139 | F66: CASSIA CHAVES LOPES | G66: 01752830369 | H66: 31594 | I66: =IF(C66<>"-",O$3,O$2) -> 32.12 | J66: 11
A67: 46129 | B67: FRONTIER | C67: ROD 9C57 | D67: CUJUPE | E67: 46142 | F67: LOUREDIR CANTANHEDE | G67: 02919330330 | H67: 31721 | I67: =IF(C67<>"-",O$3,O$2) -> 481.76 | J67: 250
A68: 46129 | B68: - | C68: - | D68: CUJUPE | E68: 46142 | F68: CASSIA CHAVES LOPES | G68: 01752830369 | H68: 31594 | I68: =IF(C68<>"-",O$3,O$2) -> 32.12 | J68: 11
H70: TOTAL | I70: =SUM(I59:I69) -> 3918.32 | L70: PAGO | M70: SIM
A71: MAIO
A72: 46142 | B72: - | C72: - | D72: PONTA DA ESPERA | E72: 46148 | F72: Telciane Martins Feitosa Rios | G72: 035.213.903-06 | H72: 32888 | I72: =IF(C72<>"-",O$3,O$2) -> 32.12 | J72: 11
A73: 46142 | B73: - | C73: - | D73: PONTA DA ESPERA | E73: 46148 | F73: Nelciane Mesquita Pinheiro | G73: 025.214.993-90 | H73: 31777 | I73: =IF(C73<>"-",O$3,O$2) -> 32.12 | J73: 11
A74: 46142 | B74: FRONTIER | C74: RON9A11 | D74: PONTA DA ESPERA | E74: 46148 | F74: Tardelly Souza Sipaúba | G74: 880.230.013-53 | H74: 30258 | I74: =IF(C74<>"-",O$3,O$2) -> 481.76 | J74: 143
A75: 46142 | B75: - | C75: - | D75: PONTA DA ESPERA | E75: 46148 | F75: Francisca Inacia Cordeiro da Silva | G75: 404.925.243-00 | H75: 25235 | I75: =IF(C75<>"-",O$3,O$2) -> 32.12 | J75: 11
A76: 46142 | B76: - | C76: - | D76: PONTA DA ESPERA | E76: 46148 | F76: Kelly Inaiane Nalva dos Santos Dias | G76: 004.719.233-03 | H76: 31006 | I76: =IF(C76<>"-",O$3,O$2) -> 32.12 | J76: 11
A77: 46142 | B77: - | C77: - | D77: CUJUPE | E77: 46150 | F77: Telciane Martins Feitosa Rios | G77: 035.213.903-06 | H77: 32888 | I77: =IF(C77<>"-",O$3,O$2) -> 32.12 | J77: 11
A78: 46142 | B78: - | C78: - | D78: CUJUPE | E78: 46150 | F78: Nelciane Mesquita Pinheiro | G78: 025.214.993-90 | H78: 31777 | I78: =IF(C78<>"-",O$3,O$2) -> 32.12 | J78: 11
A79: 46142 | B79: FRONTIER | C79: RON9A11 | D79: CUJUPE | E79: 46150 | F79: Tardelly Souza Sipaúba | G79: 880.230.013-53 | H79: 30258 | I79: =IF(C79<>"-",O$3,O$2) -> 481.76 | J79: 143
A80: 46142 | B80: - | C80: - | D80: CUJUPE | E80: 46150 | F80: Francisca Inacia Cordeiro da Silva | G80: 404.925.243-00 | H80: 25235 | I80: =IF(C80<>"-",O$3,O$2) -> 32.12 | J80: 11
A81: 46142 | B81: - | C81: - | D81: CUJUPE | E81: 46150 | F81: Kelly Inaiane Nalva dos Santos Dias | G81: 004.719.233-03 | H81: 31006 | I81: =IF(C81<>"-",O$3,O$2) -> 32.12 | J81: 11
A82: 46142 | B82: - | C82: - | D82: PONTA DA ESPERA | E82: 46148 | F82: Jaqueline Marques de Oliveira Moucherek | G82: 856.680.873-87 | H82: 29238 | I82: =IF(C82<>"-",O$3,O$2) -> 32.12 | J82: 11
A83: 46142 | B83: - | C83: - | D83: PONTA DA ESPERA | E83: 46148 | F83: Beatriz Regina Lopes Veras | G83: 653.384.723-68 | H83: 29493 | I83: =IF(C83<>"-",O$3,O$2) -> 32.12 | J83: 11
... A91: 46142 | B91: - | C91: - | D91: CUJUPE | E91: 46148 | F91: Cassia Lopes Chaves | G91: 017.528.303-69 | H91: 31594 | I91: =IF(C91<>"-",O$3,O$2) -> 32.12 | J91: 11
A92: 46142 | B92: FRONTIER | C92: RON9A11 | D92: PONTA DA ESPERA | E92: 46150 | F92: Clailton Ferreira Silva | G92: 70427003334 | H92: 31959 | I92: =IF(C92<>"-",O$3,O$2) -> 481.76 | J92: 143
A93: 46142 | B93: - | C93: - | D93: PONTA DA ESPERA | E93: 46150 | F93: Luana Menezes Fonseca Oliveira | G93: 02544696397 | H93: 35133 | I93: =IF(C93<>"-",O$3,O$2) -> 32.12 | J93: 11
A94: 46142 | B94: - | C94: - | D94: PONTA DA ESPERA | E94: 46150 | F94: Tamires Lowayne Soares Pinheiro Braga | G94: 61159022313 | H94: 27013 | I94: =IF(C94<>"-",O$3,O$2) -> 32.12 | J94: 11
A95: 46142 | B95: FRONTIER | C95: RON9A11 | D95: CUJUPE | E95: 46150 | F95: Clailton Ferreira Silva | G95: 70427003334 | H95: 31959 | I95: =IF(C95<>"-",O$3,O$2) -> 481.76 | J95: 143
A96: 46142 | B96: - | C96: - | D96: CUJUPE | E96: 46150 | F96: Luana Menezes Fonseca Oliveira | G96: 02544696397 | H96: 35133 | I96: =IF(C96<>"-",O$3,O$2) -> 32.12 | J96: 11
A97: 46142 | B97: - | C97: - | D97: CUJUPE | E97: 46150 | F97: Tamires Lowayne Soares Pinheiro Braga | G97: 61159022313 | H97: 27013 | I97: =IF(C97<>"-",O$3,O$2) -> 32.12 | J97: 11 | M97: 2069.85
A98: 46148 | B98: TIGGO 5X | C98: ROD 9C57 | D98: CUJUPE | E98: 46153 | F98: LOUREDIR CANTANHEDE | G98: 02919330330 | H98: 31721 | I98: =IF(C98<>"-",O$3,O$2) -> 481.76 | J98: 143 | M98: =I102-M97 -> 2426.63
A99: 46148 | B99: TIGGO 5X | C99: ROD 9C57 | D99: PONTA DA ESPERA | E99: 46157 | F99: LOUREDIR CANTANHEDE | G99: 02919330330 | H99: 31721 | I99: =IF(C99<>"-",O$3,O$2) -> 481.76 | J99: 143
H102: TOTAL | I102: =SUM(I72:I101) -> 4496.48 | J102: =SUM(J72:J101) -> 1364 | K102: =I102-J102 -> 3132.48 | L102: EM ABERTO | M102: NÃO
A103: JUNHO | M103: NOVOS VALORES
A104: 46169 | B104: TIGGO 5X | C104: ROD 9C57 | D104: CUJUPE | E104: 46179 | F104: LOUREDIR CANTANHEDE | G104: 02919330330 | H104: 31721 | M104: VLR PEDESTRE | N104: 32.12
A105: 46169 | B105: TIGGO 5X | C105: ROD 9C57 | D105: PONTA DA ESPERA | E105: 46183 | F105: LOUREDIR CANTANHEDE | G105: 02919330330 | H105: 31721 | M105: VLR CARRO | N105: 481.76
